{
  "cells": [
    {
      "type": "opm.Object",
      "mid": "dd5397fb-3e80-4e9d-b1ed-5e039a88c519",
      "eid": "j_332",
      "label": "OPD Construct",
      "x": 70,
      "y": 806,
      "w": 12,
      "h": 5,
      "svg": {
        "rect": {
          "id": "v-1759",
          "fill": "#fdffff",
          "magnet": "true",
          "stroke-width": "4",
          "stroke-dasharray": "0",
          "width": "135",
          "height": "60",
          "stroke": "#70E483",
          "filter": "url(#dropShadowv-3-1352970975)"
        },
        "text": {
          "fill": "#000000",
          "class": "joint-port-label",
          "transform": "matrix(1,0,0,1,-15,0)",
          "id": "v-1767",
          "text-anchor": "end"
        },
        "circle": {
          "fill": "transparent",
          "height": "2",
          "magnet": "true",
          "r": "2",
          "stroke": "transparent",
          "width": "2",
          "port": "84ae1b06-8014-4180-97a3-99197fdfdaf0",
          "port-group": "aaa",
          "class": "joint-port-body",
          "id": "v-1961"
        }
      }
    },
    {
      "type": "opm.Object",
      "mid": "8eb2bb06-00ea-4fab-af87-fef06cda7eb4",
      "eid": "j_333",
      "label": "OPD",
      "x": 54,
      "y": 797,
      "w": 11,
      "h": 5,
      "svg": {
        "rect": {
          "id": "v-1769",
          "fill": "#FFFFFF",
          "magnet": "true",
          "stroke-width": "2",
          "stroke-dasharray": "0",
          "width": "135",
          "height": "60",
          "stroke": "#70E483",
          "filter": "url(#dropShadowv-3-1352970975)"
        },
        "text": {
          "id": "v-1768",
          "font-size": "14",
          "fill": "#000002",
          "font-family": "Arial",
          "text-anchor": "middle",
          "font-weight": "600",
          "transform": "matrix(1,0,0,1,66.7,24.7)"
        }
      }
    },
    {
      "type": "opm.Object",
      "mid": "3682fea6-f735-4f9a-b36f-6dc73330fe24",
      "eid": "j_334",
      "label": "OPL Sentence",
      "x": 88,
      "y": 806,
      "w": 11,
      "h": 5,
      "svg": {
        "rect": {
          "id": "v-1773",
          "fill": "#FFFFFF",
          "magnet": "true",
          "stroke-width": "2",
          "stroke-dasharray": "0",
          "width": "135",
          "height": "60",
          "stroke": "#70E483",
          "filter": "url(#dropShadowv-3-1352970975)"
        },
        "text": {
          "id": "v-1772",
          "font-size": "14",
          "fill": "#000002",
          "font-family": "Arial",
          "text-anchor": "middle",
          "font-weight": "600",
          "transform": "matrix(1,0,0,1,65.6,30.6)"
        }
      }
    },
    {
      "type": "opm.Object",
      "mid": "c4339496-5a6b-405c-8e52-448ffe2a2c00",
      "eid": "j_335",
      "label": "Link Set",
      "x": 71,
      "y": 824,
      "w": 12,
      "h": 5,
      "svg": {
        "rect": {
          "id": "v-1777",
          "fill": "#FFFFFF",
          "magnet": "true",
          "stroke-width": "2",
          "stroke-dasharray": "0",
          "width": "135",
          "height": "60",
          "stroke": "#70E483",
          "filter": "url(#dropShadowv-3-1352970975)"
        },
        "text": {
          "fill": "#000000",
          "class": "joint-port-label",
          "transform": "matrix(1,0,0,1,-15,0)",
          "id": "v-1783",
          "text-anchor": "end"
        },
        "circle": {
          "fill": "transparent",
          "height": "2",
          "magnet": "true",
          "r": "2",
          "stroke": "transparent",
          "width": "2",
          "port": "e08a2a9d-9329-49d7-9a57-d1ccf6995dce",
          "port-group": "aaa",
          "class": "joint-port-body",
          "id": "v-2013"
        }
      }
    },
    {
      "type": "opm.Object",
      "mid": "c727e7ef-4fa2-47c6-93d2-072e49648ffd",
      "eid": "j_336",
      "label": "Thing Set",
      "x": 84,
      "y": 813,
      "w": 19,
      "h": 6,
      "svg": {
        "rect": {
          "id": "v-1785",
          "fill": "#FFFFFF",
          "magnet": "true",
          "stroke-width": "2",
          "stroke-dasharray": "0",
          "width": "224.846",
          "height": "70",
          "stroke": "#70E483",
          "filter": "url(#dropShadowv-3-1352970975)"
        },
        "text": {
          "fill": "#000000",
          "class": "joint-port-label",
          "transform": "matrix(1,0,0,1,-15,0)",
          "id": "v-1789",
          "text-anchor": "end"
        },
        "circle": {
          "fill": "transparent",
          "height": "2",
          "magnet": "true",
          "r": "2",
          "stroke": "transparent",
          "width": "2",
          "port": "b564c86d-b498-4164-b149-1a23926038d1",
          "port-group": "aaa",
          "class": "joint-port-body",
          "id": "v-2008"
        }
      }
    },
    {
      "type": "opm.Object",
      "mid": "ee76473c-d80d-425f-b2d2-f384c53518df",
      "eid": "j_337",
      "label": "Basic Construct",
      "x": 50,
      "y": 814,
      "w": 11,
      "h": 5,
      "svg": {
        "rect": {
          "id": "v-1791",
          "fill": "#fdffff",
          "magnet": "true",
          "stroke-width": "2",
          "stroke-dasharray": "0",
          "width": "135",
          "height": "60",
          "stroke": "#70E483",
          "filter": "url(#dropShadowv-3-1352970975)"
        },
        "text": {
          "id": "v-1790",
          "font-size": "14",
          "fill": "#000002",
          "font-family": "Arial",
          "text-anchor": "middle",
          "font-weight": "600",
          "transform": "matrix(1,0,0,1,64,30.6)"
        }
      }
    },
    {
      "type": "opm.Object",
      "mid": "91ea9df4-47ed-49cf-b475-34c8a7f2e848",
      "eid": "j_338",
      "label": "Size",
      "x": 70,
      "y": 831,
      "w": 13,
      "h": 6,
      "svg": {
        "rect": {
          "id": "v-1795",
          "fill": "#fdffff",
          "magnet": "true",
          "stroke-width": "2",
          "stroke-dasharray": "0",
          "width": "150",
          "height": "70",
          "stroke": "#70E483",
          "filter": "url(#dropShadowv-3-1352970975)"
        },
        "text": {
          "id": "v-1794",
          "font-size": "14",
          "fill": "#000002",
          "font-family": "Arial",
          "text-anchor": "middle",
          "font-weight": "600",
          "transform": "matrix(1,0,0,1,73.1,7.6)"
        }
      }
    },
    {
      "type": "opm.Object",
      "mid": "b44fe3bd-4f72-4979-8872-7915ed0edd4e",
      "eid": "j_339",
      "label": "Size",
      "x": 70,
      "y": 840,
      "w": 13,
      "h": 6,
      "svg": {
        "rect": {
          "id": "v-1799",
          "fill": "#fdffff",
          "magnet": "true",
          "stroke-width": "2",
          "stroke-dasharray": "0",
          "width": "150",
          "height": "70",
          "stroke": "#70E483",
          "filter": "url(#dropShadowv-3-1352970975)"
        },
        "text": {
          "id": "v-1798",
          "font-size": "14",
          "fill": "#000002",
          "font-family": "Arial",
          "text-anchor": "middle",
          "font-weight": "600",
          "transform": "matrix(1,0,0,1,73.1,7.6)"
        }
      }
    },
    {
      "type": "opm.Object",
      "mid": "a27da27d-92f1-4151-94d7-a4f4ffb8f21a",
      "eid": "j_340",
      "label": "Element",
      "x": 103,
      "y": 823,
      "w": 11,
      "h": 5,
      "svg": {
        "rect": {
          "id": "v-1803",
          "fill": "#fdffff",
          "magnet": "true",
          "stroke-width": "4",
          "stroke-dasharray": "0",
          "width": "135",
          "height": "60",
          "stroke": "#70E483",
          "filter": "url(#dropShadowv-3-1352970975)"
        },
        "text": {
          "id": "v-1802",
          "font-size": "14",
          "fill": "#000002",
          "font-family": "Arial",
          "text-anchor": "middle",
          "font-weight": "600",
          "transform": "matrix(1,0,0,1,64,30.6)"
        }
      }
    },
    {
      "type": "opm.Object",
      "mid": "fa1544bd-a5b2-4cff-974d-38919db94ec1",
      "eid": "j_341",
      "label": "Link",
      "x": 88,
      "y": 833,
      "w": 11,
      "h": 5,
      "svg": {
        "rect": {
          "id": "v-1807",
          "fill": "#FFFFFF",
          "magnet": "true",
          "stroke-width": "2",
          "stroke-dasharray": "0",
          "width": "130",
          "height": "60",
          "stroke": "#70E483",
          "filter": "url(#dropShadowv-3-1352970975)"
        },
        "text": {
          "id": "v-1806",
          "font-size": "14",
          "fill": "#000002",
          "font-family": "Arial",
          "text-anchor": "middle",
          "font-weight": "600",
          "transform": "matrix(1,0,0,1,63.1,24.7)"
        }
      }
    },
    {
      "type": "opm.Object",
      "mid": "fffa1d8c-e8fd-46c0-b6ec-96b7d4df5a5f",
      "eid": "j_342",
      "label": "Thing",
      "x": 101,
      "y": 833,
      "w": 11,
      "h": 5,
      "svg": {
        "rect": {
          "id": "v-1811",
          "fill": "#FFFFFF",
          "magnet": "true",
          "stroke-width": "4",
          "stroke-dasharray": "0",
          "width": "130",
          "height": "60",
          "stroke": "#70E483",
          "filter": "url(#dropShadowv-3-1352970975)"
        },
        "text": {
          "id": "v-1810",
          "font-size": "14",
          "fill": "#000002",
          "font-family": "Arial",
          "text-anchor": "middle",
          "font-weight": "600",
          "transform": "matrix(1,0,0,1,63.4,24.7)"
        }
      }
    },
    {
      "type": "opm.Process",
      "mid": "5b9ee3be-e082-4154-9d45-a0460b795239",
      "eid": "j_343",
      "label": "Connecting",
      "x": 87,
      "y": 821,
      "w": 11,
      "h": 5,
      "svg": {
        "ellipse": {
          "class": "mainEllipse",
          "magnet": "true",
          "id": "v-1815",
          "fill": "#fdffff",
          "stroke-width": "2",
          "stroke-dasharray": "0",
          "width": "10",
          "height": "10",
          "stroke": "#3BC3FF",
          "rx": "67.5",
          "ry": "30",
          "cx": "67.5",
          "cy": "30",
          "filter": "url(#dropShadowv-3-1352970975)"
        },
        "text": {
          "fill": "#000000",
          "class": "joint-port-label",
          "transform": "matrix(1,0,0,1,-15,0)",
          "id": "v-1819",
          "text-anchor": "end"
        },
        "circle": {
          "fill": "transparent",
          "height": "2",
          "magnet": "true",
          "r": "2",
          "stroke": "transparent",
          "width": "2",
          "port": "577113bd-9147-4e7c-a13d-2706840797b6",
          "port-group": "aaa",
          "class": "joint-port-body",
          "id": "v-2029"
        }
      }
    },
    {
      "type": "opm.State",
      "mid": "50d5b565-121d-4b3b-9eae-602b6c899914",
      "eid": "j_344",
      "label": "1",
      "x": 71,
      "y": 834,
      "w": 5,
      "h": 3,
      "svg": {
        "rect": {
          "id": "v-1822",
          "class": "inner",
          "fill": "white",
          "magnet": "true",
          "stroke-width": "0",
          "stroke": "#808000",
          "rx": "5",
          "ry": "5",
          "width": "50",
          "height": "30",
          "transform": "matrix(1,0,0,1,5,5)"
        },
        "text": {
          "id": "v-1820",
          "font-size": "14",
          "fill": "#000000",
          "font-family": "Arial, helvetica, sans-serif",
          "text-anchor": "middle",
          "font-weight": "300",
          "transform": "matrix(1,0,0,1,28.1,9.7)"
        }
      }
    },
    {
      "type": "opm.State",
      "mid": "6f097423-9d7c-4f5d-ac12-3fcbbd873c89",
      "eid": "j_345",
      "label": ">=2",
      "x": 77,
      "y": 834,
      "w": 5,
      "h": 3,
      "svg": {
        "rect": {
          "id": "v-1833",
          "class": "inner",
          "fill": "white",
          "magnet": "true",
          "stroke-width": "0",
          "stroke": "#808000",
          "rx": "5",
          "ry": "5",
          "width": "50",
          "height": "30",
          "transform": "matrix(1,0,0,1,5,5)"
        },
        "text": {
          "id": "v-1831",
          "font-size": "14",
          "fill": "#000000",
          "font-family": "Arial, helvetica, sans-serif",
          "text-anchor": "middle",
          "font-weight": "300",
          "transform": "matrix(1,0,0,1,28.1,15.6)"
        }
      }
    },
    {
      "type": "opm.State",
      "mid": "9e121fde-d98c-4968-8301-b2c86e19d155",
      "eid": "j_346",
      "label": "2",
      "x": 71,
      "y": 843,
      "w": 5,
      "h": 3,
      "svg": {
        "rect": {
          "id": "v-1844",
          "class": "inner",
          "fill": "#ffffff",
          "magnet": "true",
          "stroke-width": "0",
          "stroke": "#808000",
          "rx": "5",
          "ry": "5",
          "width": "50",
          "height": "30",
          "transform": "matrix(1,0,0,1,5,5)"
        },
        "text": {
          "id": "v-1842",
          "font-size": "14",
          "fill": "#000000",
          "font-family": "Arial, helvetica, sans-serif",
          "text-anchor": "middle",
          "font-weight": "300",
          "transform": "matrix(1,0,0,1,28.1,9.7)"
        }
      }
    },
    {
      "type": "opm.State",
      "mid": "180e14e8-47b0-4659-90b1-44506c8ea26b",
      "eid": "j_347",
      "label": ">=3",
      "x": 77,
      "y": 843,
      "w": 5,
      "h": 3,
      "svg": {
        "rect": {
          "id": "v-1855",
          "class": "inner",
          "fill": "#ffffff",
          "magnet": "true",
          "stroke-width": "0",
          "stroke": "#808000",
          "rx": "5",
          "ry": "5",
          "width": "50",
          "height": "30",
          "transform": "matrix(1,0,0,1,5,5)"
        },
        "text": {
          "id": "v-1853",
          "font-size": "14",
          "fill": "#000000",
          "font-family": "Arial, helvetica, sans-serif",
          "text-anchor": "middle",
          "font-weight": "300",
          "transform": "matrix(1,0,0,1,28.1,15.6)"
        }
      }
    },
    {
      "type": "opm.State",
      "mid": "86532701-601d-4f90-b168-2a4c559d3ae7",
      "eid": "j_348",
      "label": "disconnected",
      "x": 93,
      "y": 816,
      "w": 9,
      "h": 3,
      "svg": {
        "rect": {
          "id": "v-1866",
          "class": "inner",
          "fill": "#ffffff",
          "magnet": "true",
          "stroke-width": "0",
          "stroke": "#808000",
          "rx": "5",
          "ry": "5",
          "width": "97",
          "height": "30",
          "transform": "matrix(1,0,0,1,5,5)"
        },
        "text": {
          "id": "v-1864",
          "font-size": "14",
          "fill": "#000000",
          "font-family": "Arial, helvetica, sans-serif",
          "text-anchor": "middle",
          "font-weight": "300",
          "transform": "matrix(1,0,0,1,51.5,15.6)"
        }
      }
    },
    {
      "type": "opm.State",
      "mid": "1faa844f-7a1e-46fa-a67a-97b163236c67",
      "eid": "j_349",
      "label": "connected",
      "x": 85,
      "y": 816,
      "w": 7,
      "h": 3,
      "svg": {
        "rect": {
          "id": "v-1877",
          "class": "inner",
          "fill": "#ffffff",
          "magnet": "true",
          "stroke-width": "2",
          "stroke": "#808000",
          "rx": "5",
          "ry": "5",
          "width": "77.84600000000002",
          "height": "30",
          "transform": "matrix(1,0,0,1,5,5)"
        },
        "text": {
          "id": "v-1875",
          "font-size": "14",
          "fill": "#000000",
          "font-family": "Arial, helvetica, sans-serif",
          "text-anchor": "middle",
          "font-weight": "300",
          "transform": "matrix(1,0,0,1,42,15.6)"
        }
      }
    },
    {
      "type": "opm.TriangleAgg",
      "mid": "0db42a79-ef78-4035-b698-76f9e1a6eb73",
      "eid": "j_350",
      "label": "",
      "x": 66,
      "y": 802,
      "w": 3,
      "h": 3
    },
    {
      "type": "opm.Link",
      "mid": "b9ce93a6-ca7f-4e95-b3a3-88c5ef0e0934",
      "eid": "j_351",
      "label": "",
      "x": 65,
      "y": 799,
      "w": 1,
      "h": 3
    },
    {
      "type": "opm.Link",
      "mid": "12ab8446-c751-4fec-9a5f-18e2590e0428",
      "eid": "j_352",
      "label": "+",
      "x": 67,
      "y": 803,
      "w": 4,
      "h": 4
    },
    {
      "type": "opm.Link",
      "mid": "33c1602e-d3fe-4766-b02e-2501fb37ad20",
      "eid": "j_353",
      "label": "",
      "x": 82,
      "y": 808,
      "w": 6,
      "h": 0
    },
    {
      "type": "opm.TriangleAgg",
      "mid": "81421e24-219e-4417-ae3b-1c336b97b1c2",
      "eid": "j_354",
      "label": "",
      "x": 66,
      "y": 811,
      "w": 3,
      "h": 3
    },
    {
      "type": "opm.Link",
      "mid": "c77b6559-6f2a-458d-80d7-2574d92be803",
      "eid": "j_355",
      "label": "",
      "x": 67,
      "y": 809,
      "w": 3,
      "h": 2
    },
    {
      "type": "opm.Link",
      "mid": "b03dbbc4-5123-4e98-ae0d-7b7daa1dabeb",
      "eid": "j_356",
      "label": "",
      "x": 67,
      "y": 813,
      "w": 4,
      "h": 13
    },
    {
      "type": "opm.Link",
      "mid": "533e604c-0f49-4f27-a1a7-7f47c10db65f",
      "eid": "j_357",
      "label": "",
      "x": 67,
      "y": 813,
      "w": 17,
      "h": 3
    },
    {
      "type": "opm.TriangleAgg",
      "mid": "6673c5a1-6148-4eb9-b574-3461806fb9e4",
      "eid": "j_358",
      "label": "",
      "x": 54,
      "y": 809,
      "w": 3,
      "h": 3
    },
    {
      "type": "opm.Link",
      "mid": "5f64f862-353e-409f-8099-576e794c97c2",
      "eid": "j_359",
      "label": "",
      "x": 56,
      "y": 808,
      "w": 15,
      "h": 1
    },
    {
      "type": "opm.Link",
      "mid": "509171f5-29c9-4fc4-878b-a9c14e42ebbc",
      "eid": "j_360",
      "label": "",
      "x": 55,
      "y": 811,
      "w": 0,
      "h": 3
    },
    {
      "type": "opm.TriangleAgg",
      "mid": "adcfc486-4785-4647-ba0c-353a96e2781e",
      "eid": "j_361",
      "label": "",
      "x": 66,
      "y": 829,
      "w": 3,
      "h": 3
    },
    {
      "type": "opm.Link",
      "mid": "9c732768-cc21-411e-aa07-1dd69e2dcfa7",
      "eid": "j_362",
      "label": "",
      "x": 67,
      "y": 828,
      "w": 3,
      "h": 1
    },
    {
      "type": "opm.Link",
      "mid": "8983a67f-b734-45da-a98e-25c884c62dd3",
      "eid": "j_363",
      "label": "",
      "x": 67,
      "y": 831,
      "w": 3,
      "h": 3
    },
    {
      "type": "opm.TriangleAgg",
      "mid": "b7a204db-7441-428e-bb7e-b1661d981c31",
      "eid": "j_364",
      "label": "",
      "x": 54,
      "y": 825,
      "w": 3,
      "h": 3
    },
    {
      "type": "opm.Link",
      "mid": "9f054ce7-083e-44c3-b440-3906d2a112de",
      "eid": "j_365",
      "label": "",
      "x": 55,
      "y": 819,
      "w": 0,
      "h": 6
    },
    {
      "type": "opm.Link",
      "mid": "d0032e85-e328-47f6-ab7e-73e97f7b5347",
      "eid": "j_366",
      "label": "",
      "x": 56,
      "y": 827,
      "w": 15,
      "h": 8
    },
    {
      "type": "opm.Link",
      "mid": "80650a86-c188-4bf5-a14a-d9376ba2b3b4",
      "eid": "j_367",
      "label": "",
      "x": 56,
      "y": 827,
      "w": 16,
      "h": 17
    },
    {
      "type": "opm.TriangleAgg",
      "mid": "374f901d-cf34-4a44-96cc-caeb57f26e03",
      "eid": "j_368",
      "label": "",
      "x": 116,
      "y": 825,
      "w": 3,
      "h": 3
    },
    {
      "type": "opm.Link",
      "mid": "2a224213-b801-40f8-8527-5c6f4ff34073",
      "eid": "j_369",
      "label": "",
      "x": 103,
      "y": 816,
      "w": 14,
      "h": 9
    },
    {
      "type": "opm.Link",
      "mid": "7ce54bd9-8e64-4a76-af96-f3ad098bc8ed",
      "eid": "j_370",
      "label": "2..*",
      "x": 113,
      "y": 827,
      "w": 4,
      "h": 8
    },
    {
      "type": "opm.TriangleAgg",
      "mid": "c24db179-1576-42f9-a032-0b93a0f2e5f3",
      "eid": "j_371",
      "label": "",
      "x": 88,
      "y": 829,
      "w": 3,
      "h": 3
    },
    {
      "type": "opm.Link",
      "mid": "33fc6eb0-7018-4fdd-9eb4-790529e0e89c",
      "eid": "j_372",
      "label": "",
      "x": 82,
      "y": 827,
      "w": 7,
      "h": 3
    },
    {
      "type": "opm.Link",
      "mid": "3765364c-a8a0-4510-a3be-9fc7a6b46402",
      "eid": "j_373",
      "label": "+",
      "x": 88,
      "y": 832,
      "w": 3,
      "h": 4
    },
    {
      "type": "opm.TriangleAgg",
      "mid": "6917c74b-798c-45d9-add2-d21f37a38fe4",
      "eid": "j_374",
      "label": "",
      "x": 99,
      "y": 828,
      "w": 3,
      "h": 3
    },
    {
      "type": "opm.Link",
      "mid": "b88f6374-3e7a-40d6-b2ff-a358bb4c0e02",
      "eid": "j_375",
      "label": "",
      "x": 100,
      "y": 825,
      "w": 2,
      "h": 3
    },
    {
      "type": "opm.Link",
      "mid": "3cb6a2cb-e215-4bc1-923c-ab3cfb13f4ed",
      "eid": "j_376",
      "label": "",
      "x": 100,
      "y": 830,
      "w": 1,
      "h": 5
    },
    {
      "type": "opm.Link",
      "mid": "9100c4bd-9c32-4409-bd1c-0196879f152e",
      "eid": "j_377",
      "label": "",
      "x": 100,
      "y": 830,
      "w": 1,
      "h": 5
    },
    {
      "type": "opm.TriangleAgg",
      "mid": "80729d8f-2bc4-4b85-a7a7-f335af7af41a",
      "eid": "j_378",
      "label": "",
      "x": 120,
      "y": 825,
      "w": 3,
      "h": 3
    },
    {
      "type": "opm.Link",
      "mid": "ba40e59b-0ef5-42a8-8be0-3d3b4b9ac2ff",
      "eid": "j_379",
      "label": "",
      "x": 103,
      "y": 815,
      "w": 19,
      "h": 10
    },
    {
      "type": "opm.Link",
      "mid": "979f8199-4e15-42af-84e6-e2afb5868f27",
      "eid": "j_380",
      "label": "",
      "x": 83,
      "y": 827,
      "w": 39,
      "h": 16
    },
    {
      "type": "opm.Link",
      "mid": "f9d3d57f-7679-4138-b824-411977b472e4",
      "eid": "j_381",
      "label": "",
      "x": 82,
      "y": 825,
      "w": 5,
      "h": 1
    },
    {
      "type": "opm.Link",
      "mid": "01e2a975-e5b5-4e5b-a63b-29eda81358f8",
      "eid": "j_382",
      "label": "",
      "x": 89,
      "y": 818,
      "w": 2,
      "h": 3
    },
    {
      "type": "opm.Link",
      "mid": "c9a46861-4e43-4c63-af0f-f6b0d1a6d4bc",
      "eid": "j_383",
      "label": "",
      "x": 94,
      "y": 818,
      "w": 2,
      "h": 3
    },
    {
      "type": "opm.TriangleAgg",
      "mid": "3f8954aa-95d4-4772-8f69-db07bf7e6f84",
      "eid": "j_384",
      "label": "",
      "x": 78,
      "y": 812,
      "w": 3,
      "h": 3
    },
    {
      "type": "opm.Link",
      "mid": "1371bf16-8b3b-4615-b4c3-02b785375e23",
      "eid": "j_385",
      "label": "",
      "x": 79,
      "y": 811,
      "w": 0,
      "h": 2
    },
    {
      "type": "opm.Link",
      "mid": "bdc71b45-9835-43a3-9849-24ec432065a5",
      "eid": "j_386",
      "label": "",
      "x": 79,
      "y": 815,
      "w": 9,
      "h": 8
    },
    {
      "type": "opm.Object",
      "mid": "dd5397fb-3e80-4e9d-b1ed-5e039a88c519",
      "eid": "j_277",
      "label": "OPD Construct",
      "x": 643,
      "y": 198,
      "w": 137,
      "h": 62,
      "svg": {
        "rect": {
          "id": "v-1445",
          "fill": "#fdffff",
          "magnet": "true",
          "stroke-width": "4",
          "stroke-dasharray": "0",
          "width": "135",
          "height": "60",
          "stroke": "#70E483",
          "filter": "url(#dropShadowv-2-1352970975)"
        },
        "text": {
          "fill": "#000000",
          "class": "joint-port-label",
          "transform": "matrix(1,0,0,1,-15,0)",
          "id": "v-1453",
          "text-anchor": "end"
        },
        "circle": {
          "fill": "transparent",
          "height": "2",
          "magnet": "true",
          "r": "2",
          "stroke": "transparent",
          "width": "2",
          "port": "84ae1b06-8014-4180-97a3-99197fdfdaf0",
          "port-group": "aaa",
          "class": "joint-port-body",
          "id": "v-1647"
        }
      }
    },
    {
      "type": "opm.Object",
      "mid": "8eb2bb06-00ea-4fab-af87-fef06cda7eb4",
      "eid": "j_278",
      "label": "OPD",
      "x": 450,
      "y": 93,
      "w": 135,
      "h": 60,
      "svg": {
        "rect": {
          "id": "v-1455",
          "fill": "#FFFFFF",
          "magnet": "true",
          "stroke-width": "2",
          "stroke-dasharray": "0",
          "width": "135",
          "height": "60",
          "stroke": "#70E483",
          "filter": "url(#dropShadowv-2-1352970975)"
        },
        "text": {
          "id": "v-1454",
          "font-size": "14",
          "fill": "#000002",
          "font-family": "Arial",
          "text-anchor": "middle",
          "font-weight": "600",
          "transform": "matrix(1,0,0,1,67.5,23.8)"
        }
      }
    },
    {
      "type": "opm.Object",
      "mid": "3682fea6-f735-4f9a-b36f-6dc73330fe24",
      "eid": "j_279",
      "label": "OPL Sentence",
      "x": 851,
      "y": 203,
      "w": 135,
      "h": 60,
      "svg": {
        "rect": {
          "id": "v-1459",
          "fill": "#FFFFFF",
          "magnet": "true",
          "stroke-width": "2",
          "stroke-dasharray": "0",
          "width": "135",
          "height": "60",
          "stroke": "#70E483",
          "filter": "url(#dropShadowv-2-1352970975)"
        },
        "text": {
          "id": "v-1458",
          "font-size": "14",
          "fill": "#000002",
          "font-family": "Arial",
          "text-anchor": "middle",
          "font-weight": "600",
          "transform": "matrix(1,0,0,1,67.4,23.8)"
        }
      }
    },
    {
      "type": "opm.Object",
      "mid": "c4339496-5a6b-405c-8e52-448ffe2a2c00",
      "eid": "j_280",
      "label": "Link Set",
      "x": 645,
      "y": 418,
      "w": 139,
      "h": 60,
      "svg": {
        "rect": {
          "id": "v-1463",
          "fill": "#FFFFFF",
          "magnet": "true",
          "stroke-width": "2",
          "stroke-dasharray": "0",
          "width": "135",
          "height": "60",
          "stroke": "#70E483",
          "filter": "url(#dropShadowv-2-1352970975)"
        },
        "text": {
          "fill": "#000000",
          "class": "joint-port-label",
          "transform": "matrix(1,0,0,1,-15,0)",
          "id": "v-1469",
          "text-anchor": "end"
        },
        "circle": {
          "fill": "transparent",
          "height": "2",
          "magnet": "true",
          "r": "2",
          "stroke": "transparent",
          "width": "2",
          "port": "e08a2a9d-9329-49d7-9a57-d1ccf6995dce",
          "port-group": "aaa",
          "class": "joint-port-body",
          "id": "v-1699"
        }
      }
    },
    {
      "type": "opm.Object",
      "mid": "c727e7ef-4fa2-47c6-93d2-072e49648ffd",
      "eid": "j_281",
      "label": "Thing Set",
      "x": 800,
      "y": 289,
      "w": 227,
      "h": 70,
      "svg": {
        "rect": {
          "id": "v-1471",
          "fill": "#FFFFFF",
          "magnet": "true",
          "stroke-width": "2",
          "stroke-dasharray": "0",
          "width": "224.846",
          "height": "70",
          "stroke": "#70E483",
          "filter": "url(#dropShadowv-2-1352970975)"
        },
        "text": {
          "fill": "#000000",
          "class": "joint-port-label",
          "transform": "matrix(1,0,0,1,-15,0)",
          "id": "v-1475",
          "text-anchor": "end"
        },
        "circle": {
          "fill": "transparent",
          "height": "2",
          "magnet": "true",
          "r": "2",
          "stroke": "transparent",
          "width": "2",
          "port": "b564c86d-b498-4164-b149-1a23926038d1",
          "port-group": "aaa",
          "class": "joint-port-body",
          "id": "v-1694"
        }
      }
    },
    {
      "type": "opm.Object",
      "mid": "ee76473c-d80d-425f-b2d2-f384c53518df",
      "eid": "j_282",
      "label": "Basic Construct",
      "x": 400,
      "y": 297,
      "w": 135,
      "h": 60,
      "svg": {
        "rect": {
          "id": "v-1477",
          "fill": "#fdffff",
          "magnet": "true",
          "stroke-width": "2",
          "stroke-dasharray": "0",
          "width": "135",
          "height": "60",
          "stroke": "#70E483",
          "filter": "url(#dropShadowv-2-1352970975)"
        },
        "text": {
          "id": "v-1476",
          "font-size": "14",
          "fill": "#000002",
          "font-family": "Arial",
          "text-anchor": "middle",
          "font-weight": "600",
          "transform": "matrix(1,0,0,1,67.3,23.8)"
        }
      }
    },
    {
      "type": "opm.Object",
      "mid": "91ea9df4-47ed-49cf-b475-34c8a7f2e848",
      "eid": "j_283",
      "label": "Size",
      "x": 640,
      "y": 501,
      "w": 150,
      "h": 70,
      "svg": {
        "rect": {
          "id": "v-1481",
          "fill": "#fdffff",
          "magnet": "true",
          "stroke-width": "2",
          "stroke-dasharray": "0",
          "width": "150",
          "height": "70",
          "stroke": "#70E483",
          "filter": "url(#dropShadowv-2-1352970975)"
        },
        "text": {
          "id": "v-1480",
          "font-size": "14",
          "fill": "#000002",
          "font-family": "Arial",
          "text-anchor": "middle",
          "font-weight": "600",
          "transform": "matrix(1,0,0,1,74.9,8.8)"
        }
      }
    },
    {
      "type": "opm.Object",
      "mid": "b44fe3bd-4f72-4979-8872-7915ed0edd4e",
      "eid": "j_284",
      "label": "Size",
      "x": 642,
      "y": 606,
      "w": 150,
      "h": 70,
      "svg": {
        "rect": {
          "id": "v-1485",
          "fill": "#fdffff",
          "magnet": "true",
          "stroke-width": "2",
          "stroke-dasharray": "0",
          "width": "150",
          "height": "70",
          "stroke": "#70E483",
          "filter": "url(#dropShadowv-2-1352970975)"
        },
        "text": {
          "id": "v-1484",
          "font-size": "14",
          "fill": "#000002",
          "font-family": "Arial",
          "text-anchor": "middle",
          "font-weight": "600",
          "transform": "matrix(1,0,0,1,74.9,8.8)"
        }
      }
    },
    {
      "type": "opm.Object",
      "mid": "a27da27d-92f1-4151-94d7-a4f4ffb8f21a",
      "eid": "j_285",
      "label": "Element",
      "x": 1021,
      "y": 403,
      "w": 135,
      "h": 60,
      "svg": {
        "rect": {
          "id": "v-1489",
          "fill": "#fdffff",
          "magnet": "true",
          "stroke-width": "4",
          "stroke-dasharray": "0",
          "width": "135",
          "height": "60",
          "stroke": "#70E483",
          "filter": "url(#dropShadowv-2-1352970975)"
        },
        "text": {
          "id": "v-1488",
          "font-size": "14",
          "fill": "#000002",
          "font-family": "Arial",
          "text-anchor": "middle",
          "font-weight": "600",
          "transform": "matrix(1,0,0,1,67.3,23.8)"
        }
      }
    },
    {
      "type": "opm.Object",
      "mid": "fa1544bd-a5b2-4cff-974d-38919db94ec1",
      "eid": "j_286",
      "label": "Link",
      "x": 856,
      "y": 523,
      "w": 130,
      "h": 60,
      "svg": {
        "rect": {
          "id": "v-1493",
          "fill": "#FFFFFF",
          "magnet": "true",
          "stroke-width": "2",
          "stroke-dasharray": "0",
          "width": "130",
          "height": "60",
          "stroke": "#70E483",
          "filter": "url(#dropShadowv-2-1352970975)"
        },
        "text": {
          "id": "v-1492",
          "font-size": "14",
          "fill": "#000002",
          "font-family": "Arial",
          "text-anchor": "middle",
          "font-weight": "600",
          "transform": "matrix(1,0,0,1,64.9,23.8)"
        }
      }
    },
    {
      "type": "opm.Object",
      "mid": "fffa1d8c-e8fd-46c0-b6ec-96b7d4df5a5f",
      "eid": "j_287",
      "label": "Thing",
      "x": 1009,
      "y": 523,
      "w": 130,
      "h": 60,
      "svg": {
        "rect": {
          "id": "v-1497",
          "fill": "#FFFFFF",
          "magnet": "true",
          "stroke-width": "4",
          "stroke-dasharray": "0",
          "width": "130",
          "height": "60",
          "stroke": "#70E483",
          "filter": "url(#dropShadowv-2-1352970975)"
        },
        "text": {
          "id": "v-1496",
          "font-size": "14",
          "fill": "#000002",
          "font-family": "Arial",
          "text-anchor": "middle",
          "font-weight": "600",
          "transform": "matrix(1,0,0,1,65,23.8)"
        }
      }
    },
    {
      "type": "opm.Process",
      "mid": "5b9ee3be-e082-4154-9d45-a0460b795239",
      "eid": "j_288",
      "label": "Connecting",
      "x": 838,
      "y": 382,
      "w": 135,
      "h": 60,
      "svg": {
        "ellipse": {
          "class": "mainEllipse",
          "magnet": "true",
          "id": "v-1719",
          "fill": "#fdffff",
          "stroke-width": "2",
          "stroke-dasharray": "0",
          "width": "10",
          "height": "10",
          "stroke": "#3BC3FF",
          "rx": "67.5",
          "ry": "30",
          "cx": "67.5",
          "cy": "30",
          "filter": "url(#dropShadowv-2-1352970975)"
        },
        "text": {
          "fill": "#000000",
          "class": "joint-port-label",
          "transform": "matrix(1,0,0,1,-15,0)",
          "id": "v-1505",
          "text-anchor": "end"
        },
        "circle": {
          "fill": "transparent",
          "height": "2",
          "magnet": "true",
          "r": "2",
          "stroke": "transparent",
          "width": "2",
          "port": "577113bd-9147-4e7c-a13d-2706840797b6",
          "port-group": "aaa",
          "class": "joint-port-body",
          "id": "v-1715"
        }
      }
    },
    {
      "type": "opm.State",
      "mid": "50d5b565-121d-4b3b-9eae-602b6c899914",
      "eid": "j_289",
      "label": "1",
      "x": 650,
      "y": 530,
      "w": 60,
      "h": 30,
      "svg": {
        "rect": {
          "id": "v-1508",
          "class": "inner",
          "fill": "white",
          "magnet": "true",
          "stroke-width": "0",
          "stroke": "#808000",
          "rx": "5",
          "ry": "5",
          "width": "50",
          "height": "30",
          "transform": "matrix(1,0,0,1,5,5)"
        },
        "text": {
          "id": "v-1506",
          "font-size": "14",
          "fill": "#000000",
          "font-family": "Arial, helvetica, sans-serif",
          "text-anchor": "middle",
          "font-weight": "300",
          "transform": "matrix(1,0,0,1,29.9,8.8)"
        }
      }
    },
    {
      "type": "opm.State",
      "mid": "6f097423-9d7c-4f5d-ac12-3fcbbd873c89",
      "eid": "j_290",
      "label": ">=2",
      "x": 720,
      "y": 530,
      "w": 60,
      "h": 30,
      "svg": {
        "rect": {
          "id": "v-1519",
          "class": "inner",
          "fill": "white",
          "magnet": "true",
          "stroke-width": "0",
          "stroke": "#808000",
          "rx": "5",
          "ry": "5",
          "width": "50",
          "height": "30",
          "transform": "matrix(1,0,0,1,5,5)"
        },
        "text": {
          "id": "v-1517",
          "font-size": "14",
          "fill": "#000000",
          "font-family": "Arial, helvetica, sans-serif",
          "text-anchor": "middle",
          "font-weight": "300",
          "transform": "matrix(1,0,0,1,29.9,8.8)"
        }
      }
    },
    {
      "type": "opm.State",
      "mid": "9e121fde-d98c-4968-8301-b2c86e19d155",
      "eid": "j_291",
      "label": "2",
      "x": 652,
      "y": 635,
      "w": 60,
      "h": 30,
      "svg": {
        "rect": {
          "id": "v-1530",
          "class": "inner",
          "fill": "#ffffff",
          "magnet": "true",
          "stroke-width": "0",
          "stroke": "#808000",
          "rx": "5",
          "ry": "5",
          "width": "50",
          "height": "30",
          "transform": "matrix(1,0,0,1,5,5)"
        },
        "text": {
          "id": "v-1528",
          "font-size": "14",
          "fill": "#000000",
          "font-family": "Arial, helvetica, sans-serif",
          "text-anchor": "middle",
          "font-weight": "300",
          "transform": "matrix(1,0,0,1,29.9,8.8)"
        }
      }
    },
    {
      "type": "opm.State",
      "mid": "180e14e8-47b0-4659-90b1-44506c8ea26b",
      "eid": "j_292",
      "label": ">=3",
      "x": 722,
      "y": 635,
      "w": 60,
      "h": 30,
      "svg": {
        "rect": {
          "id": "v-1541",
          "class": "inner",
          "fill": "#ffffff",
          "magnet": "true",
          "stroke-width": "0",
          "stroke": "#808000",
          "rx": "5",
          "ry": "5",
          "width": "50",
          "height": "30",
          "transform": "matrix(1,0,0,1,5,5)"
        },
        "text": {
          "id": "v-1539",
          "font-size": "14",
          "fill": "#000000",
          "font-family": "Arial, helvetica, sans-serif",
          "text-anchor": "middle",
          "font-weight": "300",
          "transform": "matrix(1,0,0,1,29.9,8.8)"
        }
      }
    },
    {
      "type": "opm.State",
      "mid": "86532701-601d-4f90-b168-2a4c559d3ae7",
      "eid": "j_293",
      "label": "disconnected",
      "x": 908,
      "y": 318,
      "w": 107,
      "h": 30,
      "svg": {
        "rect": {
          "id": "v-1552",
          "class": "inner",
          "fill": "#ffffff",
          "magnet": "true",
          "stroke-width": "0",
          "stroke": "#808000",
          "rx": "5",
          "ry": "5",
          "width": "97",
          "height": "30",
          "transform": "matrix(1,0,0,1,5,5)"
        },
        "text": {
          "id": "v-1550",
          "font-size": "14",
          "fill": "#000000",
          "font-family": "Arial, helvetica, sans-serif",
          "text-anchor": "middle",
          "font-weight": "300",
          "transform": "matrix(1,0,0,1,53.5,8.8)"
        }
      }
    },
    {
      "type": "opm.State",
      "mid": "1faa844f-7a1e-46fa-a67a-97b163236c67",
      "eid": "j_294",
      "label": "connected",
      "x": 810,
      "y": 318,
      "w": 88,
      "h": 30,
      "svg": {
        "rect": {
          "id": "v-1563",
          "class": "inner",
          "fill": "#ffffff",
          "magnet": "true",
          "stroke-width": "2",
          "stroke": "#808000",
          "rx": "5",
          "ry": "5",
          "width": "77.84600000000002",
          "height": "30",
          "transform": "matrix(1,0,0,1,5,5)"
        },
        "text": {
          "id": "v-1561",
          "font-size": "14",
          "fill": "#000000",
          "font-family": "Arial, helvetica, sans-serif",
          "text-anchor": "middle",
          "font-weight": "300",
          "transform": "matrix(1,0,0,1,43.9,8.8)"
        }
      }
    },
    {
      "type": "opm.TriangleAgg",
      "mid": "0db42a79-ef78-4035-b698-76f9e1a6eb73",
      "eid": "j_295",
      "label": "",
      "x": 586,
      "y": 152,
      "w": 30,
      "h": 30
    },
    {
      "type": "opm.Link",
      "mid": "b9ce93a6-ca7f-4e95-b3a3-88c5ef0e0934",
      "eid": "j_296",
      "label": "",
      "x": 585,
      "y": 123,
      "w": 16,
      "h": 31
    },
    {
      "type": "opm.Link",
      "mid": "12ab8446-c751-4fec-9a5f-18e2590e0428",
      "eid": "j_297",
      "label": "+",
      "x": 601,
      "y": 172,
      "w": 45,
      "h": 43
    },
    {
      "type": "opm.Link",
      "mid": "33c1602e-d3fe-4766-b02e-2501fb37ad20",
      "eid": "j_298",
      "label": "",
      "x": 780,
      "y": 230,
      "w": 71,
      "h": 1
    },
    {
      "type": "opm.TriangleAgg",
      "mid": "81421e24-219e-4417-ae3b-1c336b97b1c2",
      "eid": "j_299",
      "label": "",
      "x": 587,
      "y": 265,
      "w": 30,
      "h": 30
    },
    {
      "type": "opm.Link",
      "mid": "c77b6559-6f2a-458d-80d7-2574d92be803",
      "eid": "j_300",
      "label": "",
      "x": 602,
      "y": 239,
      "w": 41,
      "h": 28
    },
    {
      "type": "opm.Link",
      "mid": "b03dbbc4-5123-4e98-ae0d-7b7daa1dabeb",
      "eid": "j_301",
      "label": "",
      "x": 602,
      "y": 290,
      "w": 45,
      "h": 158
    },
    {
      "type": "opm.Link",
      "mid": "533e604c-0f49-4f27-a1a7-7f47c10db65f",
      "eid": "j_302",
      "label": "",
      "x": 602,
      "y": 290,
      "w": 198,
      "h": 34
    },
    {
      "type": "opm.TriangleAgg",
      "mid": "6673c5a1-6148-4eb9-b574-3461806fb9e4",
      "eid": "j_303",
      "label": "",
      "x": 453,
      "y": 237,
      "w": 30,
      "h": 30
    },
    {
      "type": "opm.Link",
      "mid": "5f64f862-353e-409f-8099-576e794c97c2",
      "eid": "j_304",
      "label": "",
      "x": 468,
      "y": 229,
      "w": 177,
      "h": 10
    },
    {
      "type": "opm.Link",
      "mid": "509171f5-29c9-4fc4-878b-a9c14e42ebbc",
      "eid": "j_305",
      "label": "",
      "x": 468,
      "y": 262,
      "w": 1,
      "h": 35
    },
    {
      "type": "opm.TriangleAgg",
      "mid": "adcfc486-4785-4647-ba0c-353a96e2781e",
      "eid": "j_306",
      "label": "",
      "x": 591,
      "y": 471,
      "w": 30,
      "h": 30
    },
    {
      "type": "opm.Link",
      "mid": "9c732768-cc21-411e-aa07-1dd69e2dcfa7",
      "eid": "j_307",
      "label": "",
      "x": 606,
      "y": 466,
      "w": 39,
      "h": 7
    },
    {
      "type": "opm.Link",
      "mid": "8983a67f-b734-45da-a98e-25c884c62dd3",
      "eid": "j_308",
      "label": "",
      "x": 606,
      "y": 496,
      "w": 34,
      "h": 40
    },
    {
      "type": "opm.TriangleAgg",
      "mid": "b7a204db-7441-428e-bb7e-b1661d981c31",
      "eid": "j_309",
      "label": "",
      "x": 453,
      "y": 428,
      "w": 30,
      "h": 30
    },
    {
      "type": "opm.Link",
      "mid": "9f054ce7-083e-44c3-b440-3906d2a112de",
      "eid": "j_310",
      "label": "",
      "x": 468,
      "y": 357,
      "w": 1,
      "h": 73
    },
    {
      "type": "opm.Link",
      "mid": "d0032e85-e328-47f6-ab7e-73e97f7b5347",
      "eid": "j_311",
      "label": "",
      "x": 468,
      "y": 453,
      "w": 182,
      "h": 92
    },
    {
      "type": "opm.Link",
      "mid": "80650a86-c188-4bf5-a14a-d9376ba2b3b4",
      "eid": "j_312",
      "label": "",
      "x": 468,
      "y": 453,
      "w": 184,
      "h": 197
    },
    {
      "type": "opm.TriangleAgg",
      "mid": "374f901d-cf34-4a44-96cc-caeb57f26e03",
      "eid": "j_313",
      "label": "",
      "x": 1174,
      "y": 431,
      "w": 30,
      "h": 30
    },
    {
      "type": "opm.Link",
      "mid": "2a224213-b801-40f8-8527-5c6f4ff34073",
      "eid": "j_314",
      "label": "",
      "x": 1025,
      "y": 324,
      "w": 164,
      "h": 109
    },
    {
      "type": "opm.Link",
      "mid": "7ce54bd9-8e64-4a76-af96-f3ad098bc8ed",
      "eid": "j_315",
      "label": "2..*",
      "x": 1139,
      "y": 456,
      "w": 50,
      "h": 97
    },
    {
      "type": "opm.TriangleAgg",
      "mid": "c24db179-1576-42f9-a032-0b93a0f2e5f3",
      "eid": "j_316",
      "label": "",
      "x": 846,
      "y": 479,
      "w": 30,
      "h": 30
    },
    {
      "type": "opm.Link",
      "mid": "33fc6eb0-7018-4fdd-9eb4-790529e0e89c",
      "eid": "j_317",
      "label": "",
      "x": 782,
      "y": 448,
      "w": 79,
      "h": 33
    },
    {
      "type": "opm.Link",
      "mid": "3765364c-a8a0-4510-a3be-9fc7a6b46402",
      "eid": "j_318",
      "label": "+",
      "x": 849,
      "y": 504,
      "w": 38,
      "h": 49
    },
    {
      "type": "opm.TriangleAgg",
      "mid": "6917c74b-798c-45d9-add2-d21f37a38fe4",
      "eid": "j_319",
      "label": "",
      "x": 981,
      "y": 466,
      "w": 30,
      "h": 30
    },
    {
      "type": "opm.Link",
      "mid": "b88f6374-3e7a-40d6-b2ff-a358bb4c0e02",
      "eid": "j_320",
      "label": "",
      "x": 996,
      "y": 433,
      "w": 25,
      "h": 35
    },
    {
      "type": "opm.Link",
      "mid": "3cb6a2cb-e215-4bc1-923c-ab3cfb13f4ed",
      "eid": "j_321",
      "label": "",
      "x": 986,
      "y": 491,
      "w": 10,
      "h": 62
    },
    {
      "type": "opm.Link",
      "mid": "9100c4bd-9c32-4409-bd1c-0196879f152e",
      "eid": "j_322",
      "label": "",
      "x": 996,
      "y": 491,
      "w": 13,
      "h": 62
    },
    {
      "type": "opm.TriangleAgg",
      "mid": "80729d8f-2bc4-4b85-a7a7-f335af7af41a",
      "eid": "j_323",
      "label": "",
      "x": 1230,
      "y": 424,
      "w": 30,
      "h": 30
    },
    {
      "type": "opm.Link",
      "mid": "ba40e59b-0ef5-42a8-8be0-3d3b4b9ac2ff",
      "eid": "j_324",
      "label": "",
      "x": 1027,
      "y": 308,
      "w": 218,
      "h": 118
    },
    {
      "type": "opm.Link",
      "mid": "979f8199-4e15-42af-84e6-e2afb5868f27",
      "eid": "j_325",
      "label": "",
      "x": 792,
      "y": 449,
      "w": 453,
      "h": 192
    },
    {
      "type": "opm.Link",
      "mid": "f9d3d57f-7679-4138-b824-411977b472e4",
      "eid": "j_326",
      "label": "",
      "x": 784,
      "y": 424,
      "w": 60,
      "h": 12
    },
    {
      "type": "opm.Link",
      "mid": "01e2a975-e5b5-4e5b-a63b-29eda81358f8",
      "eid": "j_327",
      "label": "",
      "x": 864,
      "y": 348,
      "w": 23,
      "h": 36
    },
    {
      "type": "opm.Link",
      "mid": "c9a46861-4e43-4c63-af0f-f6b0d1a6d4bc",
      "eid": "j_328",
      "label": "",
      "x": 926,
      "y": 348,
      "w": 25,
      "h": 36
    },
    {
      "type": "opm.TriangleAgg",
      "mid": "3f8954aa-95d4-4772-8f69-db07bf7e6f84",
      "eid": "j_329",
      "label": "",
      "x": 728,
      "y": 279,
      "w": 30,
      "h": 30
    },
    {
      "type": "opm.Link",
      "mid": "1371bf16-8b3b-4615-b4c3-02b785375e23",
      "eid": "j_330",
      "label": "",
      "x": 743,
      "y": 260,
      "w": 0,
      "h": 21
    },
    {
      "type": "opm.Link",
      "mid": "bdc71b45-9835-43a3-9849-24ec432065a5",
      "eid": "j_331",
      "label": "",
      "x": 743,
      "y": 304,
      "w": 102,
      "h": 93
    }
  ],
  "linkPaths": [
    {
      "type": "opm.Link",
      "mid": "b9ce93a6-ca7f-4e95-b3a3-88c5ef0e0934",
      "tag": "path",
      "jointSelector": "wrapper",
      "d": "M 390 25 L 406 25 L 406 56",
      "x1": null,
      "y1": null,
      "x2": null,
      "y2": null,
      "stroke": "transparent",
      "sw": "15",
      "markerEnd": ""
    },
    {
      "type": "opm.Link",
      "mid": "b9ce93a6-ca7f-4e95-b3a3-88c5ef0e0934",
      "tag": "path",
      "jointSelector": "line",
      "d": "M 390 25 L 406 25 L 406 56",
      "x1": null,
      "y1": null,
      "x2": null,
      "y2": null,
      "stroke": "#586D8C",
      "sw": "2",
      "markerEnd": "#v-3-1629497611)"
    },
    {
      "type": "opm.Link",
      "mid": "12ab8446-c751-4fec-9a5f-18e2590e0428",
      "tag": "path",
      "jointSelector": "wrapper",
      "d": "M 406 79 L 406 116.9 L 448 116.86",
      "x1": null,
      "y1": null,
      "x2": null,
      "y2": null,
      "stroke": "transparent",
      "sw": "15",
      "markerEnd": ""
    },
    {
      "type": "opm.Link",
      "mid": "12ab8446-c751-4fec-9a5f-18e2590e0428",
      "tag": "path",
      "jointSelector": "line",
      "d": "M 406 79 L 406 116.9 L 448 116.86",
      "x1": null,
      "y1": null,
      "x2": null,
      "y2": null,
      "stroke": "#586D8C",
      "sw": "2",
      "markerEnd": "#v-3-1447209640)"
    },
    {
      "type": "opm.Link",
      "mid": "33c1602e-d3fe-4766-b02e-2501fb37ad20",
      "tag": "path",
      "jointSelector": "wrapper",
      "d": "M 585 132.32 L 656 133.7",
      "x1": null,
      "y1": null,
      "x2": null,
      "y2": null,
      "stroke": "transparent",
      "sw": "15",
      "markerEnd": ""
    },
    {
      "type": "opm.Link",
      "mid": "33c1602e-d3fe-4766-b02e-2501fb37ad20",
      "tag": "path",
      "jointSelector": "line",
      "d": "M 585 132.32 L 656 133.7",
      "x1": null,
      "y1": null,
      "x2": null,
      "y2": null,
      "stroke": "#586D8C",
      "sw": "2",
      "markerEnd": "#v-3-971358014)"
    },
    {
      "type": "opm.Link",
      "mid": "c77b6559-6f2a-458d-80d7-2574d92be803",
      "tag": "path",
      "jointSelector": "wrapper",
      "d": "M 448 141.33 L 407 141.3 L 407 169",
      "x1": null,
      "y1": null,
      "x2": null,
      "y2": null,
      "stroke": "transparent",
      "sw": "15",
      "markerEnd": ""
    },
    {
      "type": "opm.Link",
      "mid": "c77b6559-6f2a-458d-80d7-2574d92be803",
      "tag": "path",
      "jointSelector": "line",
      "d": "M 448 141.33 L 407 141.3 L 407 169",
      "x1": null,
      "y1": null,
      "x2": null,
      "y2": null,
      "stroke": "#586D8C",
      "sw": "2",
      "markerEnd": "#v-3-1629497611)"
    },
    {
      "type": "opm.Link",
      "mid": "b03dbbc4-5123-4e98-ae0d-7b7daa1dabeb",
      "tag": "path",
      "jointSelector": "wrapper",
      "d": "M 407 192 L 407 350 L 450 350",
      "x1": null,
      "y1": null,
      "x2": null,
      "y2": null,
      "stroke": "transparent",
      "sw": "15",
      "markerEnd": ""
    },
    {
      "type": "opm.Link",
      "mid": "b03dbbc4-5123-4e98-ae0d-7b7daa1dabeb",
      "tag": "path",
      "jointSelector": "line",
      "d": "M 407 192 L 407 350 L 450 350",
      "x1": null,
      "y1": null,
      "x2": null,
      "y2": null,
      "stroke": "#586D8C",
      "sw": "2",
      "markerEnd": "#v-3-1447209640)"
    },
    {
      "type": "opm.Link",
      "mid": "533e604c-0f49-4f27-a1a7-7f47c10db65f",
      "tag": "path",
      "jointSelector": "wrapper",
      "d": "M 407 192 L 407 226 L 605 226",
      "x1": null,
      "y1": null,
      "x2": null,
      "y2": null,
      "stroke": "transparent",
      "sw": "15",
      "markerEnd": ""
    },
    {
      "type": "opm.Link",
      "mid": "533e604c-0f49-4f27-a1a7-7f47c10db65f",
      "tag": "path",
      "jointSelector": "line",
      "d": "M 407 192 L 407 226 L 605 226",
      "x1": null,
      "y1": null,
      "x2": null,
      "y2": null,
      "stroke": "#586D8C",
      "sw": "2",
      "markerEnd": "#v-3-1447209640)"
    },
    {
      "type": "opm.Link",
      "mid": "5f64f862-353e-409f-8099-576e794c97c2",
      "tag": "path",
      "jointSelector": "wrapper",
      "d": "M 448 131 L 273 131 L 273 141",
      "x1": null,
      "y1": null,
      "x2": null,
      "y2": null,
      "stroke": "transparent",
      "sw": "15",
      "markerEnd": ""
    },
    {
      "type": "opm.Link",
      "mid": "5f64f862-353e-409f-8099-576e794c97c2",
      "tag": "path",
      "jointSelector": "line",
      "d": "M 448 131 L 273 131 L 273 141",
      "x1": null,
      "y1": null,
      "x2": null,
      "y2": null,
      "stroke": "#586D8C",
      "sw": "2",
      "markerEnd": "#v-3-1629497611)"
    },
    {
      "type": "opm.Link",
      "mid": "509171f5-29c9-4fc4-878b-a9c14e42ebbc",
      "tag": "path",
      "jointSelector": "wrapper",
      "d": "M 273 164 L 273 185.7 L 272.5 185.7 L 272.5 199",
      "x1": null,
      "y1": null,
      "x2": null,
      "y2": null,
      "stroke": "transparent",
      "sw": "15",
      "markerEnd": ""
    },
    {
      "type": "opm.Link",
      "mid": "509171f5-29c9-4fc4-878b-a9c14e42ebbc",
      "tag": "path",
      "jointSelector": "line",
      "d": "M 273 164 L 273 185.7 L 272.5 185.7 L 272.5 199",
      "x1": null,
      "y1": null,
      "x2": null,
      "y2": null,
      "stroke": "#586D8C",
      "sw": "2",
      "markerEnd": "#v-3-1447209640)"
    },
    {
      "type": "opm.Link",
      "mid": "9c732768-cc21-411e-aa07-1dd69e2dcfa7",
      "tag": "path",
      "jointSelector": "wrapper",
      "d": "M 450 367.72 L 411 367.7 L 411 375",
      "x1": null,
      "y1": null,
      "x2": null,
      "y2": null,
      "stroke": "transparent",
      "sw": "15",
      "markerEnd": ""
    },
    {
      "type": "opm.Link",
      "mid": "9c732768-cc21-411e-aa07-1dd69e2dcfa7",
      "tag": "path",
      "jointSelector": "line",
      "d": "M 450 367.72 L 411 367.7 L 411 375",
      "x1": null,
      "y1": null,
      "x2": null,
      "y2": null,
      "stroke": "#586D8C",
      "sw": "2",
      "markerEnd": "#v-3-1629497611)"
    },
    {
      "type": "opm.Link",
      "mid": "8983a67f-b734-45da-a98e-25c884c62dd3",
      "tag": "path",
      "jointSelector": "wrapper",
      "d": "M 411 398 L 411 438 L 445 438",
      "x1": null,
      "y1": null,
      "x2": null,
      "y2": null,
      "stroke": "transparent",
      "sw": "15",
      "markerEnd": ""
    },
    {
      "type": "opm.Link",
      "mid": "8983a67f-b734-45da-a98e-25c884c62dd3",
      "tag": "path",
      "jointSelector": "line",
      "d": "M 411 398 L 411 438 L 445 438",
      "x1": null,
      "y1": null,
      "x2": null,
      "y2": null,
      "stroke": "#586D8C",
      "sw": "2",
      "markerEnd": "#v-3-1447209640)"
    },
    {
      "type": "opm.Link",
      "mid": "9f054ce7-083e-44c3-b440-3906d2a112de",
      "tag": "path",
      "jointSelector": "wrapper",
      "d": "M 272.5 259 L 272.5 320.6 L 273 320.6 L 273 332",
      "x1": null,
      "y1": null,
      "x2": null,
      "y2": null,
      "stroke": "transparent",
      "sw": "15",
      "markerEnd": ""
    },
    {
      "type": "opm.Link",
      "mid": "9f054ce7-083e-44c3-b440-3906d2a112de",
      "tag": "path",
      "jointSelector": "line",
      "d": "M 272.5 259 L 272.5 320.6 L 273 320.6 L 273 332",
      "x1": null,
      "y1": null,
      "x2": null,
      "y2": null,
      "stroke": "#586D8C",
      "sw": "2",
      "markerEnd": "#v-3-1629497611)"
    },
    {
      "type": "opm.Link",
      "mid": "d0032e85-e328-47f6-ab7e-73e97f7b5347",
      "tag": "path",
      "jointSelector": "wrapper",
      "d": "M 273 355 L 273 446.5 L 455 446.5",
      "x1": null,
      "y1": null,
      "x2": null,
      "y2": null,
      "stroke": "transparent",
      "sw": "15",
      "markerEnd": ""
    },
    {
      "type": "opm.Link",
      "mid": "d0032e85-e328-47f6-ab7e-73e97f7b5347",
      "tag": "path",
      "jointSelector": "line",
      "d": "M 273 355 L 273 446.5 L 455 446.5",
      "x1": null,
      "y1": null,
      "x2": null,
      "y2": null,
      "stroke": "#586D8C",
      "sw": "2",
      "markerEnd": "#v-3-1447209640)"
    },
    {
      "type": "opm.Link",
      "mid": "80650a86-c188-4bf5-a14a-d9376ba2b3b4",
      "tag": "path",
      "jointSelector": "wrapper",
      "d": "M 273 355 L 273 551.5 L 457 551.5",
      "x1": null,
      "y1": null,
      "x2": null,
      "y2": null,
      "stroke": "transparent",
      "sw": "15",
      "markerEnd": ""
    },
    {
      "type": "opm.Link",
      "mid": "80650a86-c188-4bf5-a14a-d9376ba2b3b4",
      "tag": "path",
      "jointSelector": "line",
      "d": "M 273 355 L 273 551.5 L 457 551.5",
      "x1": null,
      "y1": null,
      "x2": null,
      "y2": null,
      "stroke": "#586D8C",
      "sw": "2",
      "markerEnd": "#v-3-1447209640)"
    },
    {
      "type": "opm.Link",
      "mid": "2a224213-b801-40f8-8527-5c6f4ff34073",
      "tag": "path",
      "jointSelector": "wrapper",
      "d": "M 831.85 226 L 994 226 L 994 335",
      "x1": null,
      "y1": null,
      "x2": null,
      "y2": null,
      "stroke": "transparent",
      "sw": "15",
      "markerEnd": ""
    },
    {
      "type": "opm.Link",
      "mid": "2a224213-b801-40f8-8527-5c6f4ff34073",
      "tag": "path",
      "jointSelector": "line",
      "d": "M 831.85 226 L 994 226 L 994 335",
      "x1": null,
      "y1": null,
      "x2": null,
      "y2": null,
      "stroke": "#586D8C",
      "sw": "2",
      "markerEnd": "#v-3-1629497611)"
    },
    {
      "type": "opm.Link",
      "mid": "7ce54bd9-8e64-4a76-af96-f3ad098bc8ed",
      "tag": "path",
      "jointSelector": "wrapper",
      "d": "M 994 358 L 994 455 L 944 455",
      "x1": null,
      "y1": null,
      "x2": null,
      "y2": null,
      "stroke": "transparent",
      "sw": "15",
      "markerEnd": ""
    },
    {
      "type": "opm.Link",
      "mid": "7ce54bd9-8e64-4a76-af96-f3ad098bc8ed",
      "tag": "path",
      "jointSelector": "line",
      "d": "M 994 358 L 994 455 L 944 455",
      "x1": null,
      "y1": null,
      "x2": null,
      "y2": null,
      "stroke": "#586D8C",
      "sw": "2",
      "markerEnd": "#v-3-1447209640)"
    },
    {
      "type": "opm.Link",
      "mid": "33fc6eb0-7018-4fdd-9eb4-790529e0e89c",
      "tag": "path",
      "jointSelector": "wrapper",
      "d": "M 589 350 L 666 350 L 666 383",
      "x1": null,
      "y1": null,
      "x2": null,
      "y2": null,
      "stroke": "transparent",
      "sw": "15",
      "markerEnd": ""
    },
    {
      "type": "opm.Link",
      "mid": "33fc6eb0-7018-4fdd-9eb4-790529e0e89c",
      "tag": "path",
      "jointSelector": "line",
      "d": "M 589 350 L 666 350 L 666 383",
      "x1": null,
      "y1": null,
      "x2": null,
      "y2": null,
      "stroke": "#586D8C",
      "sw": "2",
      "markerEnd": "#v-3-1629497611)"
    },
    {
      "type": "opm.Link",
      "mid": "3765364c-a8a0-4510-a3be-9fc7a6b46402",
      "tag": "path",
      "jointSelector": "wrapper",
      "d": "M 666 406 L 666 418.3 L 654 418.3 L 654 455 L 661 455",
      "x1": null,
      "y1": null,
      "x2": null,
      "y2": null,
      "stroke": "transparent",
      "sw": "15",
      "markerEnd": ""
    },
    {
      "type": "opm.Link",
      "mid": "3765364c-a8a0-4510-a3be-9fc7a6b46402",
      "tag": "path",
      "jointSelector": "line",
      "d": "M 666 406 L 666 418.3 L 654 418.3 L 654 455 L 661 455",
      "x1": null,
      "y1": null,
      "x2": null,
      "y2": null,
      "stroke": "#586D8C",
      "sw": "2",
      "markerEnd": "#v-3-1447209640)"
    },
    {
      "type": "opm.Link",
      "mid": "b88f6374-3e7a-40d6-b2ff-a358bb4c0e02",
      "tag": "path",
      "jointSelector": "wrapper",
      "d": "M 826 335 L 801 335 L 801 370",
      "x1": null,
      "y1": null,
      "x2": null,
      "y2": null,
      "stroke": "transparent",
      "sw": "15",
      "markerEnd": ""
    },
    {
      "type": "opm.Link",
      "mid": "b88f6374-3e7a-40d6-b2ff-a358bb4c0e02",
      "tag": "path",
      "jointSelector": "line",
      "d": "M 826 335 L 801 335 L 801 370",
      "x1": null,
      "y1": null,
      "x2": null,
      "y2": null,
      "stroke": "#586D8C",
      "sw": "2",
      "markerEnd": "#v-3-1629497611)"
    },
    {
      "type": "opm.Link",
      "mid": "3cb6a2cb-e215-4bc1-923c-ab3cfb13f4ed",
      "tag": "path",
      "jointSelector": "wrapper",
      "d": "M 801 393 L 801 455 L 791 455",
      "x1": null,
      "y1": null,
      "x2": null,
      "y2": null,
      "stroke": "transparent",
      "sw": "15",
      "markerEnd": ""
    },
    {
      "type": "opm.Link",
      "mid": "3cb6a2cb-e215-4bc1-923c-ab3cfb13f4ed",
      "tag": "path",
      "jointSelector": "line",
      "d": "M 801 393 L 801 455 L 791 455",
      "x1": null,
      "y1": null,
      "x2": null,
      "y2": null,
      "stroke": "#586D8C",
      "sw": "2",
      "markerEnd": "#v-3-1447209640)"
    },
    {
      "type": "opm.Link",
      "mid": "9100c4bd-9c32-4409-bd1c-0196879f152e",
      "tag": "path",
      "jointSelector": "wrapper",
      "d": "M 801 393 L 801 455 L 814 455",
      "x1": null,
      "y1": null,
      "x2": null,
      "y2": null,
      "stroke": "transparent",
      "sw": "15",
      "markerEnd": ""
    },
    {
      "type": "opm.Link",
      "mid": "9100c4bd-9c32-4409-bd1c-0196879f152e",
      "tag": "path",
      "jointSelector": "line",
      "d": "M 801 393 L 801 455 L 814 455",
      "x1": null,
      "y1": null,
      "x2": null,
      "y2": null,
      "stroke": "#586D8C",
      "sw": "2",
      "markerEnd": "#v-3-1447209640)"
    },
    {
      "type": "opm.Link",
      "mid": "ba40e59b-0ef5-42a8-8be0-3d3b4b9ac2ff",
      "tag": "path",
      "jointSelector": "wrapper",
      "d": "M 831.85 210.11 L 1050 210.1 L 1050 328",
      "x1": null,
      "y1": null,
      "x2": null,
      "y2": null,
      "stroke": "transparent",
      "sw": "15",
      "markerEnd": ""
    },
    {
      "type": "opm.Link",
      "mid": "ba40e59b-0ef5-42a8-8be0-3d3b4b9ac2ff",
      "tag": "path",
      "jointSelector": "line",
      "d": "M 831.85 210.11 L 1050 210.1 L 1050 328",
      "x1": null,
      "y1": null,
      "x2": null,
      "y2": null,
      "stroke": "#586D8C",
      "sw": "2",
      "markerEnd": "#v-3-1629497611)"
    },
    {
      "type": "opm.Link",
      "mid": "979f8199-4e15-42af-84e6-e2afb5868f27",
      "tag": "path",
      "jointSelector": "wrapper",
      "d": "M 1050 351 L 1050 543 L 597 543",
      "x1": null,
      "y1": null,
      "x2": null,
      "y2": null,
      "stroke": "transparent",
      "sw": "15",
      "markerEnd": ""
    },
    {
      "type": "opm.Link",
      "mid": "979f8199-4e15-42af-84e6-e2afb5868f27",
      "tag": "path",
      "jointSelector": "line",
      "d": "M 1050 351 L 1050 543 L 597 543",
      "x1": null,
      "y1": null,
      "x2": null,
      "y2": null,
      "stroke": "#586D8C",
      "sw": "2",
      "markerEnd": "#v-3-1447209640)"
    },
    {
      "type": "opm.Link",
      "mid": "f9d3d57f-7679-4138-b824-411977b472e4",
      "tag": "path",
      "jointSelector": "wrapper",
      "d": "M 589 337.93 L 643 327.29",
      "x1": null,
      "y1": null,
      "x2": null,
      "y2": null,
      "stroke": "transparent",
      "sw": "15",
      "markerEnd": ""
    },
    {
      "type": "opm.Link",
      "mid": "f9d3d57f-7679-4138-b824-411977b472e4",
      "tag": "path",
      "jointSelector": "line",
      "d": "M 589 337.93 L 643 327.29",
      "x1": null,
      "y1": null,
      "x2": null,
      "y2": null,
      "stroke": "#586D8C",
      "sw": "2",
      "markerEnd": "#v-3-683989481)"
    },
    {
      "type": "opm.Link",
      "mid": "01e2a975-e5b5-4e5b-a63b-29eda81358f8",
      "tag": "path",
      "jointSelector": "wrapper",
      "d": "M 691.04 284 L 668.65 249.5",
      "x1": null,
      "y1": null,
      "x2": null,
      "y2": null,
      "stroke": "transparent",
      "sw": "15",
      "markerEnd": ""
    },
    {
      "type": "opm.Link",
      "mid": "01e2a975-e5b5-4e5b-a63b-29eda81358f8",
      "tag": "path",
      "jointSelector": "line",
      "d": "M 691.04 284 L 668.65 249.5",
      "x1": null,
      "y1": null,
      "x2": null,
      "y2": null,
      "stroke": "#586D8C",
      "sw": "2",
      "markerEnd": "#v-3475244396)"
    },
    {
      "type": "opm.Link",
      "mid": "c9a46861-4e43-4c63-af0f-f6b0d1a6d4bc",
      "tag": "path",
      "jointSelector": "wrapper",
      "d": "M 755.81 249.5 L 731.58 284",
      "x1": null,
      "y1": null,
      "x2": null,
      "y2": null,
      "stroke": "transparent",
      "sw": "15",
      "markerEnd": ""
    },
    {
      "type": "opm.Link",
      "mid": "c9a46861-4e43-4c63-af0f-f6b0d1a6d4bc",
      "tag": "path",
      "jointSelector": "line",
      "d": "M 755.81 249.5 L 731.58 284",
      "x1": null,
      "y1": null,
      "x2": null,
      "y2": null,
      "stroke": "#586D8C",
      "sw": "2",
      "markerEnd": "#v-3475244396)"
    },
    {
      "type": "opm.Link",
      "mid": "1371bf16-8b3b-4615-b4c3-02b785375e23",
      "tag": "path",
      "jointSelector": "wrapper",
      "d": "M 548 162 L 548 183",
      "x1": null,
      "y1": null,
      "x2": null,
      "y2": null,
      "stroke": "transparent",
      "sw": "15",
      "markerEnd": ""
    },
    {
      "type": "opm.Link",
      "mid": "1371bf16-8b3b-4615-b4c3-02b785375e23",
      "tag": "path",
      "jointSelector": "line",
      "d": "M 548 162 L 548 183",
      "x1": null,
      "y1": null,
      "x2": null,
      "y2": null,
      "stroke": "#586D8C",
      "sw": "2",
      "markerEnd": "#v-3-1629497611)"
    },
    {
      "type": "opm.Link",
      "mid": "bdc71b45-9835-43a3-9849-24ec432065a5",
      "tag": "path",
      "jointSelector": "wrapper",
      "d": "M 548 206 L 548 299.4 L 649.55 299.39",
      "x1": null,
      "y1": null,
      "x2": null,
      "y2": null,
      "stroke": "transparent",
      "sw": "15",
      "markerEnd": ""
    },
    {
      "type": "opm.Link",
      "mid": "bdc71b45-9835-43a3-9849-24ec432065a5",
      "tag": "path",
      "jointSelector": "line",
      "d": "M 548 206 L 548 299.4 L 649.55 299.39",
      "x1": null,
      "y1": null,
      "x2": null,
      "y2": null,
      "stroke": "#586D8C",
      "sw": "2",
      "markerEnd": "#v-3-1447209640)"
    },
    {
      "type": "opm.Link",
      "mid": "b9ce93a6-ca7f-4e95-b3a3-88c5ef0e0934",
      "tag": "path",
      "jointSelector": "wrapper",
      "d": "M 390 25 L 406 25 L 406 56",
      "x1": null,
      "y1": null,
      "x2": null,
      "y2": null,
      "stroke": "transparent",
      "sw": "15",
      "markerEnd": ""
    },
    {
      "type": "opm.Link",
      "mid": "b9ce93a6-ca7f-4e95-b3a3-88c5ef0e0934",
      "tag": "path",
      "jointSelector": "line",
      "d": "M 390 25 L 406 25 L 406 56",
      "x1": null,
      "y1": null,
      "x2": null,
      "y2": null,
      "stroke": "#586D8C",
      "sw": "2",
      "markerEnd": "#v-2-1629497611)"
    },
    {
      "type": "opm.Link",
      "mid": "12ab8446-c751-4fec-9a5f-18e2590e0428",
      "tag": "path",
      "jointSelector": "wrapper",
      "d": "M 406 79 L 406 116.9 L 448 116.86",
      "x1": null,
      "y1": null,
      "x2": null,
      "y2": null,
      "stroke": "transparent",
      "sw": "15",
      "markerEnd": ""
    },
    {
      "type": "opm.Link",
      "mid": "12ab8446-c751-4fec-9a5f-18e2590e0428",
      "tag": "path",
      "jointSelector": "line",
      "d": "M 406 79 L 406 116.9 L 448 116.86",
      "x1": null,
      "y1": null,
      "x2": null,
      "y2": null,
      "stroke": "#586D8C",
      "sw": "2",
      "markerEnd": "#v-2-1447209640)"
    },
    {
      "type": "opm.Link",
      "mid": "33c1602e-d3fe-4766-b02e-2501fb37ad20",
      "tag": "path",
      "jointSelector": "wrapper",
      "d": "M 585 132.32 L 656 133.7",
      "x1": null,
      "y1": null,
      "x2": null,
      "y2": null,
      "stroke": "transparent",
      "sw": "15",
      "markerEnd": ""
    },
    {
      "type": "opm.Link",
      "mid": "33c1602e-d3fe-4766-b02e-2501fb37ad20",
      "tag": "path",
      "jointSelector": "line",
      "d": "M 585 132.32 L 656 133.7",
      "x1": null,
      "y1": null,
      "x2": null,
      "y2": null,
      "stroke": "#586D8C",
      "sw": "2",
      "markerEnd": "#v-2-971358014)"
    },
    {
      "type": "opm.Link",
      "mid": "c77b6559-6f2a-458d-80d7-2574d92be803",
      "tag": "path",
      "jointSelector": "wrapper",
      "d": "M 448 141.33 L 407 141.3 L 407 169",
      "x1": null,
      "y1": null,
      "x2": null,
      "y2": null,
      "stroke": "transparent",
      "sw": "15",
      "markerEnd": ""
    },
    {
      "type": "opm.Link",
      "mid": "c77b6559-6f2a-458d-80d7-2574d92be803",
      "tag": "path",
      "jointSelector": "line",
      "d": "M 448 141.33 L 407 141.3 L 407 169",
      "x1": null,
      "y1": null,
      "x2": null,
      "y2": null,
      "stroke": "#586D8C",
      "sw": "2",
      "markerEnd": "#v-2-1629497611)"
    },
    {
      "type": "opm.Link",
      "mid": "b03dbbc4-5123-4e98-ae0d-7b7daa1dabeb",
      "tag": "path",
      "jointSelector": "wrapper",
      "d": "M 407 192 L 407 350 L 452 350",
      "x1": null,
      "y1": null,
      "x2": null,
      "y2": null,
      "stroke": "transparent",
      "sw": "15",
      "markerEnd": ""
    },
    {
      "type": "opm.Link",
      "mid": "b03dbbc4-5123-4e98-ae0d-7b7daa1dabeb",
      "tag": "path",
      "jointSelector": "line",
      "d": "M 407 192 L 407 350 L 452 350",
      "x1": null,
      "y1": null,
      "x2": null,
      "y2": null,
      "stroke": "#586D8C",
      "sw": "2",
      "markerEnd": "#v-2-1447209640)"
    },
    {
      "type": "opm.Link",
      "mid": "533e604c-0f49-4f27-a1a7-7f47c10db65f",
      "tag": "path",
      "jointSelector": "wrapper",
      "d": "M 407 192 L 407 226 L 605 226",
      "x1": null,
      "y1": null,
      "x2": null,
      "y2": null,
      "stroke": "transparent",
      "sw": "15",
      "markerEnd": ""
    },
    {
      "type": "opm.Link",
      "mid": "533e604c-0f49-4f27-a1a7-7f47c10db65f",
      "tag": "path",
      "jointSelector": "line",
      "d": "M 407 192 L 407 226 L 605 226",
      "x1": null,
      "y1": null,
      "x2": null,
      "y2": null,
      "stroke": "#586D8C",
      "sw": "2",
      "markerEnd": "#v-2-1447209640)"
    },
    {
      "type": "opm.Link",
      "mid": "5f64f862-353e-409f-8099-576e794c97c2",
      "tag": "path",
      "jointSelector": "wrapper",
      "d": "M 450 131 L 273 131 L 273 141",
      "x1": null,
      "y1": null,
      "x2": null,
      "y2": null,
      "stroke": "transparent",
      "sw": "15",
      "markerEnd": ""
    },
    {
      "type": "opm.Link",
      "mid": "5f64f862-353e-409f-8099-576e794c97c2",
      "tag": "path",
      "jointSelector": "line",
      "d": "M 450 131 L 273 131 L 273 141",
      "x1": null,
      "y1": null,
      "x2": null,
      "y2": null,
      "stroke": "#586D8C",
      "sw": "2",
      "markerEnd": "#v-2-1629497611)"
    },
    {
      "type": "opm.Link",
      "mid": "509171f5-29c9-4fc4-878b-a9c14e42ebbc",
      "tag": "path",
      "jointSelector": "wrapper",
      "d": "M 273 164 L 273 185.7 L 272.5 185.7 L 272.5 199",
      "x1": null,
      "y1": null,
      "x2": null,
      "y2": null,
      "stroke": "transparent",
      "sw": "15",
      "markerEnd": ""
    },
    {
      "type": "opm.Link",
      "mid": "509171f5-29c9-4fc4-878b-a9c14e42ebbc",
      "tag": "path",
      "jointSelector": "line",
      "d": "M 273 164 L 273 185.7 L 272.5 185.7 L 272.5 199",
      "x1": null,
      "y1": null,
      "x2": null,
      "y2": null,
      "stroke": "#586D8C",
      "sw": "2",
      "markerEnd": "#v-2-1447209640)"
    },
    {
      "type": "opm.Link",
      "mid": "9c732768-cc21-411e-aa07-1dd69e2dcfa7",
      "tag": "path",
      "jointSelector": "wrapper",
      "d": "M 450 367.72 L 411 367.7 L 411 375",
      "x1": null,
      "y1": null,
      "x2": null,
      "y2": null,
      "stroke": "transparent",
      "sw": "15",
      "markerEnd": ""
    },
    {
      "type": "opm.Link",
      "mid": "9c732768-cc21-411e-aa07-1dd69e2dcfa7",
      "tag": "path",
      "jointSelector": "line",
      "d": "M 450 367.72 L 411 367.7 L 411 375",
      "x1": null,
      "y1": null,
      "x2": null,
      "y2": null,
      "stroke": "#586D8C",
      "sw": "2",
      "markerEnd": "#v-2-1629497611)"
    },
    {
      "type": "opm.Link",
      "mid": "8983a67f-b734-45da-a98e-25c884c62dd3",
      "tag": "path",
      "jointSelector": "wrapper",
      "d": "M 411 398 L 411 438 L 445 438",
      "x1": null,
      "y1": null,
      "x2": null,
      "y2": null,
      "stroke": "transparent",
      "sw": "15",
      "markerEnd": ""
    },
    {
      "type": "opm.Link",
      "mid": "8983a67f-b734-45da-a98e-25c884c62dd3",
      "tag": "path",
      "jointSelector": "line",
      "d": "M 411 398 L 411 438 L 445 438",
      "x1": null,
      "y1": null,
      "x2": null,
      "y2": null,
      "stroke": "#586D8C",
      "sw": "2",
      "markerEnd": "#v-2-1447209640)"
    },
    {
      "type": "opm.Link",
      "mid": "9f054ce7-083e-44c3-b440-3906d2a112de",
      "tag": "path",
      "jointSelector": "wrapper",
      "d": "M 272.5 259 L 272.5 320.6 L 273 320.6 L 273 332",
      "x1": null,
      "y1": null,
      "x2": null,
      "y2": null,
      "stroke": "transparent",
      "sw": "15",
      "markerEnd": ""
    },
    {
      "type": "opm.Link",
      "mid": "9f054ce7-083e-44c3-b440-3906d2a112de",
      "tag": "path",
      "jointSelector": "line",
      "d": "M 272.5 259 L 272.5 320.6 L 273 320.6 L 273 332",
      "x1": null,
      "y1": null,
      "x2": null,
      "y2": null,
      "stroke": "#586D8C",
      "sw": "2",
      "markerEnd": "#v-2-1629497611)"
    },
    {
      "type": "opm.Link",
      "mid": "d0032e85-e328-47f6-ab7e-73e97f7b5347",
      "tag": "path",
      "jointSelector": "wrapper",
      "d": "M 273 355 L 273 446.5 L 455 446.5",
      "x1": null,
      "y1": null,
      "x2": null,
      "y2": null,
      "stroke": "transparent",
      "sw": "15",
      "markerEnd": ""
    },
    {
      "type": "opm.Link",
      "mid": "d0032e85-e328-47f6-ab7e-73e97f7b5347",
      "tag": "path",
      "jointSelector": "line",
      "d": "M 273 355 L 273 446.5 L 455 446.5",
      "x1": null,
      "y1": null,
      "x2": null,
      "y2": null,
      "stroke": "#586D8C",
      "sw": "2",
      "markerEnd": "#v-2-1447209640)"
    },
    {
      "type": "opm.Link",
      "mid": "80650a86-c188-4bf5-a14a-d9376ba2b3b4",
      "tag": "path",
      "jointSelector": "wrapper",
      "d": "M 273 355 L 273 551.5 L 457 551.5",
      "x1": null,
      "y1": null,
      "x2": null,
      "y2": null,
      "stroke": "transparent",
      "sw": "15",
      "markerEnd": ""
    },
    {
      "type": "opm.Link",
      "mid": "80650a86-c188-4bf5-a14a-d9376ba2b3b4",
      "tag": "path",
      "jointSelector": "line",
      "d": "M 273 355 L 273 551.5 L 457 551.5",
      "x1": null,
      "y1": null,
      "x2": null,
      "y2": null,
      "stroke": "#586D8C",
      "sw": "2",
      "markerEnd": "#v-2-1447209640)"
    },
    {
      "type": "opm.Link",
      "mid": "2a224213-b801-40f8-8527-5c6f4ff34073",
      "tag": "path",
      "jointSelector": "wrapper",
      "d": "M 829.85 226 L 994 226 L 994 335",
      "x1": null,
      "y1": null,
      "x2": null,
      "y2": null,
      "stroke": "transparent",
      "sw": "15",
      "markerEnd": ""
    },
    {
      "type": "opm.Link",
      "mid": "2a224213-b801-40f8-8527-5c6f4ff34073",
      "tag": "path",
      "jointSelector": "line",
      "d": "M 829.85 226 L 994 226 L 994 335",
      "x1": null,
      "y1": null,
      "x2": null,
      "y2": null,
      "stroke": "#586D8C",
      "sw": "2",
      "markerEnd": "#v-2-1629497611)"
    },
    {
      "type": "opm.Link",
      "mid": "7ce54bd9-8e64-4a76-af96-f3ad098bc8ed",
      "tag": "path",
      "jointSelector": "wrapper",
      "d": "M 994 358 L 994 455 L 944 455",
      "x1": null,
      "y1": null,
      "x2": null,
      "y2": null,
      "stroke": "transparent",
      "sw": "15",
      "markerEnd": ""
    },
    {
      "type": "opm.Link",
      "mid": "7ce54bd9-8e64-4a76-af96-f3ad098bc8ed",
      "tag": "path",
      "jointSelector": "line",
      "d": "M 994 358 L 994 455 L 944 455",
      "x1": null,
      "y1": null,
      "x2": null,
      "y2": null,
      "stroke": "#586D8C",
      "sw": "2",
      "markerEnd": "#v-2-1447209640)"
    },
    {
      "type": "opm.Link",
      "mid": "33fc6eb0-7018-4fdd-9eb4-790529e0e89c",
      "tag": "path",
      "jointSelector": "wrapper",
      "d": "M 587 350 L 666 350 L 666 383",
      "x1": null,
      "y1": null,
      "x2": null,
      "y2": null,
      "stroke": "transparent",
      "sw": "15",
      "markerEnd": ""
    },
    {
      "type": "opm.Link",
      "mid": "33fc6eb0-7018-4fdd-9eb4-790529e0e89c",
      "tag": "path",
      "jointSelector": "line",
      "d": "M 587 350 L 666 350 L 666 383",
      "x1": null,
      "y1": null,
      "x2": null,
      "y2": null,
      "stroke": "#586D8C",
      "sw": "2",
      "markerEnd": "#v-2-1629497611)"
    },
    {
      "type": "opm.Link",
      "mid": "3765364c-a8a0-4510-a3be-9fc7a6b46402",
      "tag": "path",
      "jointSelector": "wrapper",
      "d": "M 666 406 L 666 418.3 L 654 418.3 L 654 455 L 661 455",
      "x1": null,
      "y1": null,
      "x2": null,
      "y2": null,
      "stroke": "transparent",
      "sw": "15",
      "markerEnd": ""
    },
    {
      "type": "opm.Link",
      "mid": "3765364c-a8a0-4510-a3be-9fc7a6b46402",
      "tag": "path",
      "jointSelector": "line",
      "d": "M 666 406 L 666 418.3 L 654 418.3 L 654 455 L 661 455",
      "x1": null,
      "y1": null,
      "x2": null,
      "y2": null,
      "stroke": "#586D8C",
      "sw": "2",
      "markerEnd": "#v-2-1447209640)"
    },
    {
      "type": "opm.Link",
      "mid": "b88f6374-3e7a-40d6-b2ff-a358bb4c0e02",
      "tag": "path",
      "jointSelector": "wrapper",
      "d": "M 826 335 L 801 335 L 801 370",
      "x1": null,
      "y1": null,
      "x2": null,
      "y2": null,
      "stroke": "transparent",
      "sw": "15",
      "markerEnd": ""
    },
    {
      "type": "opm.Link",
      "mid": "b88f6374-3e7a-40d6-b2ff-a358bb4c0e02",
      "tag": "path",
      "jointSelector": "line",
      "d": "M 826 335 L 801 335 L 801 370",
      "x1": null,
      "y1": null,
      "x2": null,
      "y2": null,
      "stroke": "#586D8C",
      "sw": "2",
      "markerEnd": "#v-2-1629497611)"
    },
    {
      "type": "opm.Link",
      "mid": "3cb6a2cb-e215-4bc1-923c-ab3cfb13f4ed",
      "tag": "path",
      "jointSelector": "wrapper",
      "d": "M 801 393 L 801 455 L 791 455",
      "x1": null,
      "y1": null,
      "x2": null,
      "y2": null,
      "stroke": "transparent",
      "sw": "15",
      "markerEnd": ""
    },
    {
      "type": "opm.Link",
      "mid": "3cb6a2cb-e215-4bc1-923c-ab3cfb13f4ed",
      "tag": "path",
      "jointSelector": "line",
      "d": "M 801 393 L 801 455 L 791 455",
      "x1": null,
      "y1": null,
      "x2": null,
      "y2": null,
      "stroke": "#586D8C",
      "sw": "2",
      "markerEnd": "#v-2-1447209640)"
    },
    {
      "type": "opm.Link",
      "mid": "9100c4bd-9c32-4409-bd1c-0196879f152e",
      "tag": "path",
      "jointSelector": "wrapper",
      "d": "M 801 393 L 801 455 L 814 455",
      "x1": null,
      "y1": null,
      "x2": null,
      "y2": null,
      "stroke": "transparent",
      "sw": "15",
      "markerEnd": ""
    },
    {
      "type": "opm.Link",
      "mid": "9100c4bd-9c32-4409-bd1c-0196879f152e",
      "tag": "path",
      "jointSelector": "line",
      "d": "M 801 393 L 801 455 L 814 455",
      "x1": null,
      "y1": null,
      "x2": null,
      "y2": null,
      "stroke": "#586D8C",
      "sw": "2",
      "markerEnd": "#v-2-1447209640)"
    },
    {
      "type": "opm.Link",
      "mid": "ba40e59b-0ef5-42a8-8be0-3d3b4b9ac2ff",
      "tag": "path",
      "jointSelector": "wrapper",
      "d": "M 831.85 210.11 L 1050 210.1 L 1050 328",
      "x1": null,
      "y1": null,
      "x2": null,
      "y2": null,
      "stroke": "transparent",
      "sw": "15",
      "markerEnd": ""
    },
    {
      "type": "opm.Link",
      "mid": "ba40e59b-0ef5-42a8-8be0-3d3b4b9ac2ff",
      "tag": "path",
      "jointSelector": "line",
      "d": "M 831.85 210.11 L 1050 210.1 L 1050 328",
      "x1": null,
      "y1": null,
      "x2": null,
      "y2": null,
      "stroke": "#586D8C",
      "sw": "2",
      "markerEnd": "#v-2-1629497611)"
    },
    {
      "type": "opm.Link",
      "mid": "979f8199-4e15-42af-84e6-e2afb5868f27",
      "tag": "path",
      "jointSelector": "wrapper",
      "d": "M 1050 351 L 1050 543 L 597 543",
      "x1": null,
      "y1": null,
      "x2": null,
      "y2": null,
      "stroke": "transparent",
      "sw": "15",
      "markerEnd": ""
    },
    {
      "type": "opm.Link",
      "mid": "979f8199-4e15-42af-84e6-e2afb5868f27",
      "tag": "path",
      "jointSelector": "line",
      "d": "M 1050 351 L 1050 543 L 597 543",
      "x1": null,
      "y1": null,
      "x2": null,
      "y2": null,
      "stroke": "#586D8C",
      "sw": "2",
      "markerEnd": "#v-2-1447209640)"
    },
    {
      "type": "opm.Link",
      "mid": "f9d3d57f-7679-4138-b824-411977b472e4",
      "tag": "path",
      "jointSelector": "wrapper",
      "d": "M 588.96 337.93 L 648.79 326.15",
      "x1": null,
      "y1": null,
      "x2": null,
      "y2": null,
      "stroke": "transparent",
      "sw": "15",
      "markerEnd": ""
    },
    {
      "type": "opm.Link",
      "mid": "f9d3d57f-7679-4138-b824-411977b472e4",
      "tag": "path",
      "jointSelector": "line",
      "d": "M 588.96 337.93 L 648.79 326.15",
      "x1": null,
      "y1": null,
      "x2": null,
      "y2": null,
      "stroke": "#586D8C",
      "sw": "2",
      "markerEnd": "#v-2-683989481)"
    },
    {
      "type": "opm.Link",
      "mid": "01e2a975-e5b5-4e5b-a63b-29eda81358f8",
      "tag": "path",
      "jointSelector": "wrapper",
      "d": "M 691.8 285.17 L 668.65 249.5",
      "x1": null,
      "y1": null,
      "x2": null,
      "y2": null,
      "stroke": "transparent",
      "sw": "15",
      "markerEnd": ""
    },
    {
      "type": "opm.Link",
      "mid": "01e2a975-e5b5-4e5b-a63b-29eda81358f8",
      "tag": "path",
      "jointSelector": "line",
      "d": "M 691.8 285.17 L 668.65 249.5",
      "x1": null,
      "y1": null,
      "x2": null,
      "y2": null,
      "stroke": "#586D8C",
      "sw": "2",
      "markerEnd": "#v-2475244396)"
    },
    {
      "type": "opm.Link",
      "mid": "c9a46861-4e43-4c63-af0f-f6b0d1a6d4bc",
      "tag": "path",
      "jointSelector": "wrapper",
      "d": "M 755.81 249.5 L 730.62 285.36",
      "x1": null,
      "y1": null,
      "x2": null,
      "y2": null,
      "stroke": "transparent",
      "sw": "15",
      "markerEnd": ""
    },
    {
      "type": "opm.Link",
      "mid": "c9a46861-4e43-4c63-af0f-f6b0d1a6d4bc",
      "tag": "path",
      "jointSelector": "line",
      "d": "M 755.81 249.5 L 730.62 285.36",
      "x1": null,
      "y1": null,
      "x2": null,
      "y2": null,
      "stroke": "#586D8C",
      "sw": "2",
      "markerEnd": "#v-2475244396)"
    },
    {
      "type": "opm.Link",
      "mid": "1371bf16-8b3b-4615-b4c3-02b785375e23",
      "tag": "path",
      "jointSelector": "wrapper",
      "d": "M 548 162 L 548 183",
      "x1": null,
      "y1": null,
      "x2": null,
      "y2": null,
      "stroke": "transparent",
      "sw": "15",
      "markerEnd": ""
    },
    {
      "type": "opm.Link",
      "mid": "1371bf16-8b3b-4615-b4c3-02b785375e23",
      "tag": "path",
      "jointSelector": "line",
      "d": "M 548 162 L 548 183",
      "x1": null,
      "y1": null,
      "x2": null,
      "y2": null,
      "stroke": "#586D8C",
      "sw": "2",
      "markerEnd": "#v-2-1629497611)"
    },
    {
      "type": "opm.Link",
      "mid": "bdc71b45-9835-43a3-9849-24ec432065a5",
      "tag": "path",
      "jointSelector": "wrapper",
      "d": "M 548 206 L 548 299.4 L 649.55 299.39",
      "x1": null,
      "y1": null,
      "x2": null,
      "y2": null,
      "stroke": "transparent",
      "sw": "15",
      "markerEnd": ""
    },
    {
      "type": "opm.Link",
      "mid": "bdc71b45-9835-43a3-9849-24ec432065a5",
      "tag": "path",
      "jointSelector": "line",
      "d": "M 548 206 L 548 299.4 L 649.55 299.39",
      "x1": null,
      "y1": null,
      "x2": null,
      "y2": null,
      "stroke": "#586D8C",
      "sw": "2",
      "markerEnd": "#v-2-1447209640)"
    }
  ],
  "triangleAggs": [
    {
      "mid": "0db42a79-ef78-4035-b698-76f9e1a6eb73",
      "tag": "image",
      "d": null
    },
    {
      "mid": "81421e24-219e-4417-ae3b-1c336b97b1c2",
      "tag": "image",
      "d": null
    },
    {
      "mid": "6673c5a1-6148-4eb9-b574-3461806fb9e4",
      "tag": "image",
      "d": null
    },
    {
      "mid": "adcfc486-4785-4647-ba0c-353a96e2781e",
      "tag": "image",
      "d": null
    },
    {
      "mid": "b7a204db-7441-428e-bb7e-b1661d981c31",
      "tag": "image",
      "d": null
    },
    {
      "mid": "374f901d-cf34-4a44-96cc-caeb57f26e03",
      "tag": "image",
      "d": null
    },
    {
      "mid": "c24db179-1576-42f9-a032-0b93a0f2e5f3",
      "tag": "image",
      "d": null
    },
    {
      "mid": "6917c74b-798c-45d9-add2-d21f37a38fe4",
      "tag": "image",
      "d": null
    },
    {
      "mid": "80729d8f-2bc4-4b85-a7a7-f335af7af41a",
      "tag": "image",
      "d": null
    },
    {
      "mid": "3f8954aa-95d4-4772-8f69-db07bf7e6f84",
      "tag": "image",
      "d": null
    },
    {
      "mid": "0db42a79-ef78-4035-b698-76f9e1a6eb73",
      "tag": "image",
      "d": null
    },
    {
      "mid": "81421e24-219e-4417-ae3b-1c336b97b1c2",
      "tag": "image",
      "d": null
    },
    {
      "mid": "6673c5a1-6148-4eb9-b574-3461806fb9e4",
      "tag": "image",
      "d": null
    },
    {
      "mid": "adcfc486-4785-4647-ba0c-353a96e2781e",
      "tag": "image",
      "d": null
    },
    {
      "mid": "b7a204db-7441-428e-bb7e-b1661d981c31",
      "tag": "image",
      "d": null
    },
    {
      "mid": "374f901d-cf34-4a44-96cc-caeb57f26e03",
      "tag": "image",
      "d": null
    },
    {
      "mid": "c24db179-1576-42f9-a032-0b93a0f2e5f3",
      "tag": "image",
      "d": null
    },
    {
      "mid": "6917c74b-798c-45d9-add2-d21f37a38fe4",
      "tag": "image",
      "d": null
    },
    {
      "mid": "80729d8f-2bc4-4b85-a7a7-f335af7af41a",
      "tag": "image",
      "d": null
    },
    {
      "mid": "3f8954aa-95d4-4772-8f69-db07bf7e6f84",
      "tag": "image",
      "d": null
    }
  ],
  "defs": [
    {
      "id": "filter0_d",
      "tag": "filter",
      "outerHTML": "<filter _ngcontent-ng-c4130173904=\"\" id=\"filter0_d\" x=\"0\" y=\"0\" width=\"77\" height=\"51\" filterUnits=\"userSpaceOnUse\" color-interpolation-filters=\"sRGB\"><feFlood _ngcontent-ng-c4130173904=\"\" flood-opacity=\"0\" result=\"BackgroundImageFix\"></feFlood><feColorMatrix _ngcontent-ng-c4130173904=\"\" in=\"SourceAlpha\" type=\"matrix\" values=\"0 0 0 0 0 0 0 0 0 0 0 0 0 0 0 0 0 0 127 0\"></feColorMatrix><feOffset _ng"
    },
    {
      "id": "filter1_d",
      "tag": "filter",
      "outerHTML": "<filter _ngcontent-ng-c4130173904=\"\" id=\"filter1_d\" x=\"17.4333\" y=\"10\" width=\"42.1334\" height=\"31\" filterUnits=\"userSpaceOnUse\" color-interpolation-filters=\"sRGB\"><feFlood _ngcontent-ng-c4130173904=\"\" flood-opacity=\"0\" result=\"BackgroundImageFix\"></feFlood><feColorMatrix _ngcontent-ng-c4130173904=\"\" in=\"SourceAlpha\" type=\"matrix\" values=\"0 0 0 0 0 0 0 0 0 0 0 0 0 0 0 0 0 0 127 0\"></feColorMatrix><"
    },
    {
      "id": "filter0_d",
      "tag": "filter",
      "outerHTML": "<filter _ngcontent-ng-c4130173904=\"\" id=\"filter0_d\" x=\"0\" y=\"0\" width=\"77\" height=\"51\" filterUnits=\"userSpaceOnUse\" color-interpolation-filters=\"sRGB\"><feFlood _ngcontent-ng-c4130173904=\"\" flood-opacity=\"0\" result=\"BackgroundImageFix\"></feFlood><feColorMatrix _ngcontent-ng-c4130173904=\"\" in=\"SourceAlpha\" type=\"matrix\" values=\"0 0 0 0 0 0 0 0 0 0 0 0 0 0 0 0 0 0 127 0\"></feColorMatrix><feOffset _ng"
    },
    {
      "id": "filter1_d",
      "tag": "filter",
      "outerHTML": "<filter _ngcontent-ng-c4130173904=\"\" id=\"filter1_d\" x=\"17.4333\" y=\"10\" width=\"42.1333\" height=\"31\" filterUnits=\"userSpaceOnUse\" color-interpolation-filters=\"sRGB\"><feFlood _ngcontent-ng-c4130173904=\"\" flood-opacity=\"0\" result=\"BackgroundImageFix\"></feFlood><feColorMatrix _ngcontent-ng-c4130173904=\"\" in=\"SourceAlpha\" type=\"matrix\" values=\"0 0 0 0 0 0 0 0 0 0 0 0 0 0 0 0 0 0 127 0\"></feColorMatrix><"
    },
    {
      "id": "dropShadowv-3-1352970975",
      "tag": "filter",
      "outerHTML": "<filter id=\"dropShadowv-3-1352970975\" filterUnits=\"objectBoundingBox\" x=\"-1\" y=\"-1\" width=\"3\" height=\"3\"><feDropShadow stdDeviation=\"0\" dx=\"0\" dy=\"0\" flood-color=\"grey\" flood-opacity=\"1\"></feDropShadow></filter>"
    },
    {
      "id": "dropShadowv-3-1096745468",
      "tag": "filter",
      "outerHTML": "<filter id=\"dropShadowv-3-1096745468\" filterUnits=\"objectBoundingBox\" x=\"-1\" y=\"-1\" width=\"3\" height=\"3\"><feDropShadow stdDeviation=\"0\" dx=\"3\" dy=\"6\" flood-color=\"grey\" flood-opacity=\"1\"></feDropShadow></filter>"
    },
    {
      "id": "v-3937177351",
      "tag": "marker",
      "outerHTML": "<marker id=\"v-3937177351\" orient=\"auto\" overflow=\"visible\" markerUnits=\"userSpaceOnUse\"><polyline id=\"v-583\" stroke=\"#586D8C\" fill=\"none\" transform=\"rotate(180)\" d=\"\" strokeWidth=\"2\" points=\"0,0 20,-10 0,0 20,10\"></polyline></marker>"
    },
    {
      "id": "v-3-1629497611",
      "tag": "marker",
      "outerHTML": "<marker id=\"v-3-1629497611\" orient=\"auto\" overflow=\"visible\" markerUnits=\"userSpaceOnUse\"><polyline id=\"v-588\" stroke=\"rgba(88,109,140,0)\" fill=\"none\" transform=\"rotate(180)\" d=\"\" stroke-width=\"2\" points=\"0,0 -2,0\"></polyline></marker>"
    },
    {
      "id": "v-3-1447209640",
      "tag": "marker",
      "outerHTML": "<marker id=\"v-3-1447209640\" orient=\"auto\" overflow=\"visible\" markerUnits=\"userSpaceOnUse\"><path id=\"v-593\" stroke=\"none\" fill=\"#586D8C\" transform=\"rotate(180)\" d=\"\"></path></marker>"
    },
    {
      "id": "v-3-971358014",
      "tag": "marker",
      "outerHTML": "<marker id=\"v-3-971358014\" orient=\"auto\" overflow=\"visible\" markerUnits=\"userSpaceOnUse\"><polyline id=\"v-605\" stroke=\"#586D8C\" fill=\"none\" transform=\"rotate(180)\" d=\"\" strokeWidth=\"2\" points=\"0.5,0 20,10\"></polyline></marker>"
    },
    {
      "id": "v-31989495267",
      "tag": "marker",
      "outerHTML": "<marker id=\"v-31989495267\" orient=\"auto\" overflow=\"visible\" markerUnits=\"userSpaceOnUse\"><polyline id=\"v-607\" stroke=\"#586D8C\" fill=\"none\" strokeWidth=\"2\" points=\"0.5,0 20,10\"></polyline></marker>"
    },
    {
      "id": "v-3-683989481",
      "tag": "marker",
      "outerHTML": "<marker id=\"v-3-683989481\" orient=\"auto\" overflow=\"visible\" markerUnits=\"userSpaceOnUse\"><circle id=\"v-2017\" stroke=\"#586D8C\" fill=\"white\" transform=\"rotate(180)\" d=\"\" strokeWidth=\"2\" r=\"5\" cx=\"5\"></circle></marker>"
    },
    {
      "id": "v-31803607991",
      "tag": "marker",
      "outerHTML": "<marker id=\"v-31803607991\" orient=\"auto\" overflow=\"visible\" markerUnits=\"userSpaceOnUse\"><path id=\"v-2019\" stroke=\"#586D8C\" fill=\"#586D8C\"></path></marker>"
    },
    {
      "id": "v-3475244396",
      "tag": "marker",
      "outerHTML": "<marker id=\"v-3475244396\" orient=\"auto\" overflow=\"visible\" markerUnits=\"userSpaceOnUse\"><path id=\"v-2023\" stroke=\"#586D8C\" fill=\"white\" transform=\"rotate(180)\" d=\"M0,0 L23,8 L12,0 L23,-8 L0,0\" strokeWidth=\"2\"></path></marker>"
    },
    {
      "id": "dropShadowv-2-1352970975",
      "tag": "filter",
      "outerHTML": "<filter id=\"dropShadowv-2-1352970975\" filterUnits=\"objectBoundingBox\" x=\"-1\" y=\"-1\" width=\"3\" height=\"3\"><feDropShadow stdDeviation=\"0\" dx=\"0\" dy=\"0\" flood-color=\"grey\" flood-opacity=\"1\"></feDropShadow></filter>"
    },
    {
      "id": "dropShadowv-2-1096745468",
      "tag": "filter",
      "outerHTML": "<filter id=\"dropShadowv-2-1096745468\" filterUnits=\"objectBoundingBox\" x=\"-1\" y=\"-1\" width=\"3\" height=\"3\"><feDropShadow stdDeviation=\"0\" dx=\"3\" dy=\"6\" flood-color=\"grey\" flood-opacity=\"1\"></feDropShadow></filter>"
    },
    {
      "id": "v-2937177351",
      "tag": "marker",
      "outerHTML": "<marker id=\"v-2937177351\" orient=\"auto\" overflow=\"visible\" markerUnits=\"userSpaceOnUse\"><polyline id=\"v-207\" stroke=\"#586D8C\" fill=\"none\" transform=\"rotate(180)\" d=\"\" strokeWidth=\"2\" points=\"0,0 20,-10 0,0 20,10\"></polyline></marker>"
    },
    {
      "id": "v-2-1629497611",
      "tag": "marker",
      "outerHTML": "<marker id=\"v-2-1629497611\" orient=\"auto\" overflow=\"visible\" markerUnits=\"userSpaceOnUse\"><polyline id=\"v-212\" stroke=\"rgba(88,109,140,0)\" fill=\"none\" transform=\"rotate(180)\" d=\"\" stroke-width=\"2\" points=\"0,0 -2,0\"></polyline></marker>"
    },
    {
      "id": "v-2-1447209640",
      "tag": "marker",
      "outerHTML": "<marker id=\"v-2-1447209640\" orient=\"auto\" overflow=\"visible\" markerUnits=\"userSpaceOnUse\"><path id=\"v-217\" stroke=\"none\" fill=\"#586D8C\" transform=\"rotate(180)\" d=\"\"></path></marker>"
    },
    {
      "id": "v-2-971358014",
      "tag": "marker",
      "outerHTML": "<marker id=\"v-2-971358014\" orient=\"auto\" overflow=\"visible\" markerUnits=\"userSpaceOnUse\"><polyline id=\"v-229\" stroke=\"#586D8C\" fill=\"none\" transform=\"rotate(180)\" d=\"\" strokeWidth=\"2\" points=\"0.5,0 20,10\"></polyline></marker>"
    },
    {
      "id": "v-21989495267",
      "tag": "marker",
      "outerHTML": "<marker id=\"v-21989495267\" orient=\"auto\" overflow=\"visible\" markerUnits=\"userSpaceOnUse\"><polyline id=\"v-231\" stroke=\"#586D8C\" fill=\"none\" strokeWidth=\"2\" points=\"0.5,0 20,10\"></polyline></marker>"
    },
    {
      "id": "v-2-683989481",
      "tag": "marker",
      "outerHTML": "<marker id=\"v-2-683989481\" orient=\"auto\" overflow=\"visible\" markerUnits=\"userSpaceOnUse\"><circle id=\"v-1703\" stroke=\"#586D8C\" fill=\"white\" transform=\"rotate(180)\" d=\"\" strokeWidth=\"2\" r=\"5\" cx=\"5\"></circle></marker>"
    },
    {
      "id": "v-21803607991",
      "tag": "marker",
      "outerHTML": "<marker id=\"v-21803607991\" orient=\"auto\" overflow=\"visible\" markerUnits=\"userSpaceOnUse\"><path id=\"v-1705\" stroke=\"#586D8C\" fill=\"#586D8C\"></path></marker>"
    },
    {
      "id": "v-2475244396",
      "tag": "marker",
      "outerHTML": "<marker id=\"v-2475244396\" orient=\"auto\" overflow=\"visible\" markerUnits=\"userSpaceOnUse\"><path id=\"v-1709\" stroke=\"#586D8C\" fill=\"white\" transform=\"rotate(180)\" d=\"M0,0 L23,8 L12,0 L23,-8 L0,0\" strokeWidth=\"2\"></path></marker>"
    }
  ],
  "types": {
    "opm.Object": 22,
    "opm.Process": 2,
    "opm.State": 12,
    "opm.TriangleAgg": 20,
    "opm.Link": 54
  },
  "oplText": ""
}